[
  {
    "question_no.": 1,
    "Question": "Which traditional sport from Afghanistan involves two teams on horseback trying to grab a headless calf or goat carcass?",
    "Option1": "Polo",
    "Option2": "Buzkashi",
    "Option3": "Tent Pegging",
    "Option4": "Javelin Throwing",
    "Answer": "Buzkashi"
  },
  {
    "question_no.": 2,
    "Question": "What is the national sport of Canada, played on ice with sticks and a puck?",
    "Option1": "Lacrosse",
    "Option2": "Basketball",
    "Option3": "Ice Hockey",
    "Option4": "Curling",
    "Answer": "Ice Hockey"
  },
  {
    "question_no.": 3,
    "Question": "In which country did the traditional martial art of Capoeira originate, combining elements of dance, acrobatics, and music?",
    "Option1": "Cuba",
    "Option2": "Brazil",
    "Option3": "Argentina",
    "Option4": "Portugal",
    "Answer": "Brazil"
  },
  {
    "question_no.": 4,
    "Question": "What is the name of the traditional Irish sport played with a stick (hurley) and a small ball (sliotar)?",
    "Option1": "Gaelic Football",
    "Option2": "Hurling",
    "Option3": "Rugby",
    "Option4": "Curling",
    "Answer": "Hurling"
  },
  {
    "question_no.": 5,
    "Question": "Which traditional sport of Spain involves a person attempting to evade a charging bull, often in a bullring?",
    "Option1": "Judo",
    "Option2": "Fencing",
    "Option3": "Bullfighting",
    "Option4": "Jai Alai",
    "Answer": "Bullfighting"
  },
  {
    "question_no.": 6,
    "Question": "What is the national sport of India and Pakistan, a field hockey game similar to ice hockey?",
    "Option1": "Cricket",
    "Option2": "Badminton",
    "Option3": "Field Hockey",
    "Option4": "Kabaddi",
    "Answer": "Field Hockey"
  },
  {
    "question_no.": 7,
    "Question": "In which region of Scotland did the 'Highland Games' originate, featuring events like caber toss and hammer throw?",
    "Option1": "Lowlands",
    "Option2": "Highlands",
    "Option3": "Islands",
    "Option4": "Central Belt",
    "Answer": "Highlands"
  },
  {
    "question_no.": 8,
    "Question": "What is the traditional sport of Japan involving sumo wrestlers trying to force each other out of a circular ring?",
    "Option1": "Karate",
    "Option2": "Judo",
    "Option3": "Sumo Wrestling",
    "Option4": "Kendo",
    "Answer": "Sumo Wrestling"
  },
  {
    "question_no.": 9,
    "Question": "Which traditional sport from Mexico involves players using a long, curved basket to hurl a ball against a wall?",
    "Option1": "Pelota",
    "Option2": "Jai Alai",
    "Option3": "Frontenis",
    "Option4": "Racquetball",
    "Answer": "Jai Alai"
  },
  {
    "question_no.": 10,
    "Question": "What is the name of the traditional sport in the Philippines where two roosters fight in a ring, often with bladed spurs?",
    "Option1": "Arnis",
    "Option2": "Sepak Takraw",
    "Option3": "Cockfighting",
    "Option4": "Sipa",
    "Answer": "Cockfighting"
  },
  {
    "question_no.": 11,
    "Question": "Which traditional sport of Mongolia involves wrestling, horse racing, and archery, known as 'The Three Manly Games'?",
    "Option1": "Bukh",
    "Option2": "Naadam",
    "Option3": "Kuresh",
    "Option4": "Kyokushin",
    "Answer": "Naadam"
  },
  {
    "question_no.": 12,
    "Question": "In which country is Glima, a traditional form of wrestling, popular?",
    "Option1": "Sweden",
    "Option2": "Norway",
    "Option3": "Iceland",
    "Option4": "Finland",
    "Answer": "Iceland"
  },
  {
    "question_no.": 13,
    "Question": "What is the name of the traditional Indonesian martial art that combines striking, grappling, and throwing techniques?",
    "Option1": "Kung Fu",
    "Option2": "Silat",
    "Option3": "Muay Thai",
    "Option4": "Taekwondo",
    "Answer": "Silat"
  },
  {
    "question_no.": 14,
    "Question": "Which traditional sport from Central Asia involves two horse-mounted teams competing to gain possession of a goat carcass?",
    "Option1": "Chovgan",
    "Option2": "Kokpar",
    "Option3": "Polo",
    "Option4": "Jereed",
    "Answer": "Kokpar"
  },
  {
    "question_no.": 15,
    "Question": "What is the national sport of Bhutan, an archery competition using traditional bows and arrows?",
    "Option1": "Druk-yul",
    "Option2": "Archery",
    "Option3": "Pangdo",
    "Option4": "Degor",
    "Answer": "Archery"
  },
  {
    "question_no.": 16,
    "Question": "In which country is oil wrestling, or Kırkpınar, a popular traditional sport?",
    "Option1": "Greece",
    "Option2": "Turkey",
    "Option3": "Iran",
    "Option4": "Bulgaria",
    "Answer": "Turkey"
  },
  {
    "question_no.": 17,
    "Question": "What is the name of the traditional Aboriginal Australian team sport played with a ball made from possum skin?",
    "Option1": "Marn Grook",
    "Option2": "Boomerang Throwing",
    "Option3": "Wadi-Wadi",
    "Option4": "Didgeridoo Competition",
    "Answer": "Marn Grook"
  },
  {
    "question_no.": 18,
    "Question": "Which traditional sport of England involves hitting a ball with a bat and running between wickets?",
    "Option1": "Football",
    "Option2": "Cricket",
    "Option3": "Rugby",
    "Option4": "Rounders",
    "Answer": "Cricket"
  },
  {
    "question_no.": 19,
    "Question": "What is the national sport of Malaysia, a team sport similar to volleyball but played with feet, knees, and head?",
    "Option1": "Badminton",
    "Option2": "Sepak Takraw",
    "Option3": "Takraw",
    "Option4": "Silat",
    "Answer": "Sepak Takraw"
  },
  {
    "question_no.": 20,
    "Question": "In which country did the sport of Pesäpallo, a bat-and-ball game similar to baseball, originate?",
    "Option1": "Sweden",
    "Option2": "Finland",
    "Option3": "Norway",
    "Option4": "Denmark",
    "Answer": "Finland"
  },
  {
    "question_no.": 21,
    "Question": "What is the name of the traditional sport in ancient Rome that involved chariot racing?",
    "Option1": "Gladiatorial Combat",
    "Option2": "Circus Maximus Racing",
    "Option3": "Olympian Games",
    "Option4": "Pankration",
    "Answer": "Circus Maximus Racing"
  },
  {
    "question_no.": 22,
    "Question": "Which traditional sport from the Arctic regions involves pulling a heavy object while attached by a harness, often seen in Inuit communities?",
    "Option1": "Dog Sledding",
    "Option2": "Sled Pulling",
    "Option3": "Seal Hunting",
    "Option4": "Ivory Carving",
    "Answer": "Sled Pulling"
  },
  {
    "question_no.": 23,
    "Question": "What is the national sport of Mongolia, an equestrian sport where riders use a lasso-like pole to catch wild horses?",
    "Option1": "Archery",
    "Option2": "Horse Racing",
    "Option3": "Horse Catching (Ukhna)",
    "Option4": "Wrestling",
    "Answer": "Horse Catching (Ukhna)"
  },
  {
    "question_no.": 24,
    "Question": "In which country is Hurling considered a national sport?",
    "Option1": "Wales",
    "Option2": "Scotland",
    "Option3": "Ireland",
    "Option4": "England",
    "Answer": "Ireland"
  },
  {
    "question_no.": 25,
    "Question": "What is the name of the traditional sport in Thailand, a martial art known for its 'eight limbs' (fists, elbows, knees, shins)?",
    "Option1": "Karate",
    "Option2": "Taekwondo",
    "Option3": "Muay Thai",
    "Option4": "Kung Fu",
    "Answer": "Muay Thai"
  },
  {
    "question_no.": 26,
    "Question": "Which traditional sport from Switzerland involves throwing a heavy stone (Unspunnenstein) for distance?",
    "Option1": "Schwingen",
    "Option2": "Hornussen",
    "Option3": "Stone Put",
    "Option4": "Alpine Wrestling",
    "Answer": "Stone Put"
  },
  {
    "question_no.": 27,
    "Question": "What is the national sport of South Korea, a martial art characterized by head-height kicks and jumping spinning kicks?",
    "Option1": "Judo",
    "Option2": "Karate",
    "Option3": "Taekwondo",
    "Option4": "Hapkido",
    "Answer": "Taekwondo"
  },
  {
    "question_no. 28": "In which country is traditional boat racing, particularly dragon boat racing, a significant cultural and sporting event?",
    "Option1": "India",
    "Option2": "China",
    "Option3": "Egypt",
    "Option4": "Peru",
    "Answer": "China"
  },
  {
    "question_no.": 29,
    "Question": "What is the name of the traditional Native American sport, often called 'the fastest game on two feet', played with a stick and a ball?",
    "Option1": "Basketball",
    "Option2": "Lacrosse",
    "Option3": "Baseball",
    "Option4": "Football",
    "Answer": "Lacrosse"
  },
  {
    "question_no.": 30,
    "Question": "Which traditional sport from the Basque Country involves hitting a ball against a wall with bare hands or a glove?",
    "Option1": "Pelota Vasca (Basque Pelota)",
    "Option2": "Jai Alai",
    "Option3": "Fronton",
    "Option4": "Handball",
    "Answer": "Pelota Vasca (Basque Pelota)"
  },
  {
    "question_no.": 31,
    "Question": "What is the national sport of New Zealand, known for its fierce haka dance performed before matches?",
    "Option1": "Soccer",
    "Option2": "Cricket",
    "Option3": "Rugby Union",
    "Option4": "Netball",
    "Answer": "Rugby Union"
  },
  {
    "question_no.": 32,
    "Question": "In which country is Kabaddi, a team contact sport, particularly popular?",
    "Option1": "China",
    "Option2": "Japan",
    "Option3": "India",
    "Option4": "Thailand",
    "Answer": "India"
  },
  {
    "question_no.": 33,
    "Question": "What is the name of the traditional sport in Afghanistan, often considered the national sport, involving two teams of riders trying to grab a goat carcass?",
    "Option1": "Polo",
    "Option2": "Buzkashi",
    "Option3": "Chovgan",
    "Option4": "Jereed",
    "Answer": "Buzkashi"
  },
  {
    "question_no.": 34,
    "Question": "Which traditional sport from Iran involves wrestling, weightlifting, and gymnastics, often practiced in a 'Zurkhaneh'?",
    "Option1": "Varzesh-e Bastani",
    "Option2": "Pahlavani",
    "Option3": "Kuresh",
    "Option4": "Judo",
    "Answer": "Varzesh-e Bastani"
  },
  {
    "question_no.": 35,
    "Question": "What is the national sport of Scotland, played with a stick and a ball where the goal is to hit the ball into a net?",
    "Option1": "Football",
    "Option2": "Golf",
    "Option3": "Shinty",
    "Option4": "Curling",
    "Answer": "Shinty"
  },
  {
    "question_no.": 36,
    "Question": "In which country is Gaelic Football, a blend of soccer and rugby, a prominent traditional sport?",
    "Option1": "Wales",
    "Option2": "England",
    "Option3": "Ireland",
    "Option4": "Scotland",
    "Answer": "Ireland"
  },
  {
    "question_no.": 37,
    "Question": "What is the name of the traditional sport in the Canary Islands involving two wrestlers trying to throw each other off balance within a circular sand pit?",
    "Option1": "Lucha Canaria",
    "Option2": "Canarian Wrestling",
    "Option3": "Tenerife Throw",
    "Option4": "Fuerteventura Combat",
    "Answer": "Lucha Canaria"
  },
  {
    "question_no.": 38,
    "Question": "Which traditional sport from Norway involves cross-country skiing and rifle shooting?",
    "Option1": "Nordic Combined",
    "Option2": "Biathlon",
    "Option3": "Ski Jumping",
    "Option4": "Alpine Skiing",
    "Answer": "Biathlon"
  },
  {
    "question_no.": 39,
    "Question": "What is the national sport of Peru, a traditional ball game played with a small leather ball and a specialized glove?",
    "Option1": "Fronton",
    "Option2": "Pelota Vasca",
    "Option3": "Paleta Fronton",
    "Option4": "Handball",
    "Answer": "Paleta Fronton"
  },
  {
    "question_no.": 40,
    "Question": "In which country is Buzkashi a prominent traditional equestrian sport?",
    "Option1": "Uzbekistan",
    "Option2": "Kazakhstan",
    "Option3": "Afghanistan",
    "Option4": "Turkmenistan",
    "Answer": "Afghanistan"
  },
  {
    "question_no.": 41,
    "Question": "What is the name of the traditional sport in Switzerland that involves hitting a 'Nouss' (small disc) with a 'Hornuss' (long flexible stick)?",
    "Option1": "Schwingen",
    "Option2": "Hornussen",
    "Option3": "Stone Put",
    "Option4": "Alpine Skiing",
    "Answer": "Hornussen"
  },
  {
    "question_no.": 42,
    "Question": "Which traditional sport from the Inuit people involves a competition of strength, balance, and endurance, often including events like the One-Foot High Kick?",
    "Option1": "Arctic Games",
    "Option2": "Inuit Games",
    "Option3": "Winter Olympics",
    "Option4": "Snowshoe Racing",
    "Answer": "Inuit Games"
  },
  {
    "question_no.": 43,
    "Question": "What is the national sport of Uruguay, a team sport played on horseback with a ball and sticks?",
    "Option1": "Pato",
    "Option2": "Polo",
    "Option3": "Horseball",
    "Option4": "Field Hockey",
    "Answer": "Pato"
  },
  {
    "question_no.": 44,
    "Question": "In which country is Ssirum, a traditional form of wrestling where competitors hold onto a cloth belt around their opponent's waist and thigh, popular?",
    "Option1": "Japan",
    "Option2": "China",
    "Option3": "South Korea",
    "Option4": "Vietnam",
    "Answer": "South Korea"
  },
  {
    "question_no.": 45,
    "Question": "What is the name of the traditional sport in Portugal that involves bullfighting without killing the bull?",
    "Option1": "Tourada",
    "Option2": "Corrida de Touros",
    "Option3": "Folk Bullfighting",
    "Option4": "Cavalos",
    "Answer": "Tourada"
  },
  {
    "question_no.": 46,
    "Question": "Which traditional sport from Hawaii involves riding waves on a board?",
    "Option1": "Canoeing",
    "Option2": "Surfing",
    "Option3": "Outrigger Racing",
    "Option4": "Hula Dancing",
    "Answer": "Surfing"
  },
  {
    "question_no.": 47,
    "Question": "What is the national sport of Indonesia, a martial art known for its fluidity and grace, often performed in ceremonial forms?",
    "Option1": "Muay Thai",
    "Option2": "Silat",
    "Option3": "Escrima",
    "Option4": "Kali",
    "Answer": "Silat"
  },
  {
    "question_no.": 48,
    "Question": "In which country is Arnis, a traditional martial art focusing on weapon-based fighting (sticks, knives), the national sport?",
    "Option1": "Thailand",
    "Option2": "Vietnam",
    "Option3": "Philippines",
    "Option4": "Malaysia",
    "Answer": "Philippines"
  },
  {
    "question_no.": 49,
    "Question": "What is the name of the traditional sport in Nigeria where wrestlers try to take down their opponents, often with elaborate dances before the match?",
    "Option1": "Dambe",
    "Option2": "Wrestling",
    "Option3": "Boxing",
    "Option4": "Zulu Combat",
    "Answer": "Dambe"
  },
  {
    "question_no.": 50,
    "Question": "Which traditional sport from Turkey involves two camel wrestlers competing to pin or push each other out of a designated area?",
    "Option1": "Camel Racing",
    "Option2": "Camel Wrestling",
    "Option3": "Horse Wrestling",
    "Option4": "Donkey Wrestling",
    "Answer": "Camel Wrestling"
  },
  {
    "question_no.": 51,
    "Question": "What is the national sport of Sri Lanka, a volleyball-like game played with feet and head?",
    "Option1": "Cricket",
    "Option2": "Badminton",
    "Option3": "Volleyball",
    "Option4": "Rugby",
    "Answer": "Volleyball"
  },
  {
    "question_no.": 52,
    "Question": "In which country is Hurdling, a traditional athletic event, especially popular in rural competitions?",
    "Option1": "Germany",
    "Option2": "France",
    "Option3": "United Kingdom (specifically rural areas)",
    "Option4": "Australia",
    "Answer": "United Kingdom (specifically rural areas)"
  },
  {
    "question_no.": 53,
    "Question": "What is the name of the traditional sport in China where individuals use martial arts techniques to perform elaborate acrobatic routines?",
    "Option1": "Kung Fu",
    "Option2": "Wushu",
    "Option3": "Tai Chi",
    "Option4": "Shaolin Kung Fu",
    "Answer": "Wushu"
  },
  {
    "question_no.": 54,
    "Question": "Which traditional sport from the Caribbean involves throwing a stick or spear for distance and accuracy?",
    "Option1": "Cricket",
    "Option2": "Javelin Throwing",
    "Option3": "Bocce",
    "Option4": "Dominoes",
    "Answer": "Javelin Throwing"
  },
  {
    "question_no.": 55,
    "Question": "What is the national sport of France, a game played with boules (metal balls) on a gravel surface?",
    "Option1": "Tennis",
    "Option2": "Petanque",
    "Option3": "Bowling",
    "Option4": "Bocce",
    "Answer": "Petanque"
  },
  {
    "question_no.": 56,
    "Question": "In which country is Ssireum, a traditional form of Korean wrestling, a popular spectator sport?",
    "Option1": "North Korea",
    "Option2": "South Korea",
    "Option3": "Japan",
    "Option4": "China",
    "Answer": "South Korea"
  },
  {
    "question_no.": 57,
    "Question": "What is the name of the traditional sport in Italy where teams compete to throw a heavy cheese wheel down a street or road?",
    "Option1": "Formaggio Rolling",
    "Option2": "Cheese Rolling",
    "Option3": "Palio di Siena",
    "Option4": "Calcio Storico",
    "Answer": "Cheese Rolling"
  },
  {
    "question_no.": 58,
    "Question": "Which traditional sport from Argentina involves two teams on horseback trying to score goals by throwing a ball through elevated hoops?",
    "Option1": "Polo",
    "Option2": "Pato",
    "Option3": "Horseball",
    "Option4": "Tent Pegging",
    "Answer": "Pato"
  },
  {
    "question_no.": 59,
    "Question": "What is the national sport of Vietnam, a martial art known for its scissor kicks and flying techniques?",
    "Option1": "Vovinam",
    "Option2": "Viet Vo Dao",
    "Option3": "Kung Fu",
    "Option4": "Taekwondo",
    "Answer": "Vovinam"
  },
  {
    "question_no.": 60,
    "Question": "In which country is Jereed, a traditional Turkish equestrian sport involving throwing wooden javelins, still practiced?",
    "Option1": "Syria",
    "Option2": "Turkey",
    "Option3": "Greece",
    "Option4": "Egypt",
    "Answer": "Turkey"
  },
  {
    "question_no.": 61,
    "Question": "What is the name of the traditional sport in the Netherlands where two teams try to hit a wooden ball with a bat and score points by running between posts?",
    "Option1": "Korfball",
    "Option2": "Fierljeppen",
    "Option3": "Kaatsen (Frisian Handball)",
    "Option4": "Klootschieten",
    "Answer": "Kaatsen (Frisian Handball)"
  },
  {
    "question_no.": 62,
    "Question": "Which traditional sport from Pakistan involves a form of wrestling where competitors try to pin their opponents to the ground?",
    "Option1": "Kabaddi",
    "Option2": "Pehlwani (Gatka)",
    "Option3": "Lath Mar",
    "Option4": "Bazkashi",
    "Answer": "Pehlwani (Gatka)"
  },
  {
    "question_no.": 63,
    "Question": "What is the national sport of Iceland, a form of wrestling where competitors wear special straps and try to trip their opponent?",
    "Option1": "Glima",
    "Option2": "Wrestling",
    "Option3": "Judo",
    "Option4": "Sumo",
    "Answer": "Glima"
  },
  {
    "question_no.": 64,
    "Question": "In which country is 'Calcio Storico', a violent and chaotic form of football, traditionally played in Florence?",
    "Option1": "Spain",
    "Option2": "France",
    "Option3": "Italy",
    "Option4": "Germany",
    "Answer": "Italy"
  },
  {
    "question_no.": 65,
    "Question": "What is the name of the traditional sport in Japan that involves fencing with bamboo swords?",
    "Option1": "Karate",
    "Option2": "Judo",
    "Option3": "Kendo",
    "Option4": "Aikido",
    "Answer": "Kendo"
  },
  {
    "question_no.": 66,
    "Question": "Which traditional sport from Russia involves bare-knuckle fighting, often in a circular pit?",
    "Option1": "Sambo",
    "Option2": "Systema",
    "Option3": "Kulak Dzhog",
    "Option4": "Russian Boxing",
    "Answer": "Kulak Dzhog"
  },
  {
    "question_no.": 67,
    "Question": "What is the national sport of Egypt, a team sport played with a ball on a field with goals at each end?",
    "Option1": "Football (Soccer)",
    "Option2": "Handball",
    "Option3": "Volleyball",
    "Option4": "Squash",
    "Answer": "Football (Soccer)"
  },
  {
    "question_no.": 68,
    "Question": "In which country is Camel Racing a traditional sport, particularly popular in desert regions?",
    "Option1": "Australia",
    "Option2": "Saudi Arabia",
    "Option3": "Mongolia",
    "Option4": "China",
    "Answer": "Saudi Arabia"
  },
  {
    "question_no.": 69,
    "Question": "What is the name of the traditional sport in the United States, particularly popular in rodeos, involving riding a bucking horse?",
    "Option1": "Barrel Racing",
    "Option2": "Bull Riding",
    "Option3": "Bronc Riding",
    "Option4": "Roping",
    "Answer": "Bronc Riding"
  },
  {
    "question_no.": 70,
    "Question": "Which traditional sport from the Caucasus region involves a form of wrestling where competitors try to throw their opponent to the ground, often seen in Azerbaijan and Georgia?",
    "Option1": "Chidaoba",
    "Option2": "Kuresh",
    "Option3": "Sambo",
    "Option4": "Judo",
    "Answer": "Chidaoba"
  },
  {
    "question_no.": 71,
    "Question": "What is the national sport of Cuba, a bat-and-ball game similar to baseball?",
    "Option1": "Soccer",
    "Option2": "Basketball",
    "Option3": "Baseball",
    "Option4": "Volleyball",
    "Answer": "Baseball"
  },
  {
    "question_no.": 72,
    "Question": "In which country is Bossaball, a mix of volleyball, football, and gymnastics played on an inflatable court with trampolines, popular?",
    "Option1": "Brazil",
    "Option2": "Spain",
    "Option3": "Belgium",
    "Option4": "Netherlands",
    "Answer": "Spain"
  },
  {
    "question_no.": 73,
    "Question": "What is the name of the traditional sport in Scotland where competitors throw a large, tapered log (caber) end-over-end?",
    "Option1": "Hammer Throw",
    "Option2": "Stone Put",
    "Option3": "Caber Toss",
    "Option4": "Shotput",
    "Answer": "Caber Toss"
  },
  {
    "question_no.": 74,
    "Question": "Which traditional sport from ancient Greece involved a combination of boxing and wrestling, with no rules against biting or gouging?",
    "Option1": "Boxing",
    "Option2": "Wrestling",
    "Option3": "Pankration",
    "Option4": "Gladiatorial Combat",
    "Answer": "Pankration"
  },
  {
    "question_no.": 75,
    "Question": "What is the national sport of Bangladesh, a team sport where players attempt to tag opponents in a restricted area?",
    "Option1": "Cricket",
    "Option2": "Football (Soccer)",
    "Option3": "Kabaddi",
    "Option4": "Field Hockey",
    "Answer": "Kabaddi"
  },
  {
    "question_no.": 76,
    "Question": "In which country is Bull Leaping, an ancient Minoan ritual and sport, depicted in frescoes?",
    "Option1": "Greece",
    "Option2": "Crete",
    "Option3": "Italy",
    "Option4": "Egypt",
    "Answer": "Crete"
  },
  {
    "question_no.": 77,
    "Question": "What is the name of the traditional sport in Ireland where two teams use their hands and feet to move a ball up and down a field towards goals?",
    "Option1": "Hurling",
    "Option2": "Gaelic Football",
    "Option3": "Rugby",
    "Option4": "Soccer",
    "Answer": "Gaelic Football"
  },
  {
    "question_no.": 78,
    "Question": "Which traditional sport from the Middle East involves horseback riders using long spears to collect rings from the ground?",
    "Option1": "Polo",
    "Option2": "Tent Pegging",
    "Option3": "Jereed",
    "Option4": "Horse Archery",
    "Answer": "Tent Pegging"
  },
  {
    "question_no.": 79,
    "Question": "What is the national sport of Mexico, a complex equestrian art form involving horse handling, roping, and bull riding elements?",
    "Option1": "Charreada",
    "Option2": "Rodeo",
    "Option3": "Bullfighting",
    "Option4": "Polo",
    "Answer": "Charreada"
  },
  {
    "question_no.": 80,
    "Question": "In which country is Glima, a traditional wrestling style with distinct grips and throws, considered a national sport?",
    "Option1": "Sweden",
    "Option2": "Denmark",
    "Option3": "Iceland",
    "Option4": "Finland",
    "Answer": "Iceland"
  },
  {
    "question_no.": 81,
    "Question": "What is the name of the traditional sport in the United Kingdom, particularly in rural areas, where competitors try to hit a ball through hoops embedded in the ground using mallets?",
    "Option1": "Croquet",
    "Option2": "Bowls",
    "Option3": "Bocce",
    "Option4": "Petanque",
    "Answer": "Croquet"
  },
  {
    "question_no.": 82,
    "Question": "Which traditional sport from the Philippines involves kicking a ball over a net using only the feet, knees, and head?",
    "Option1": "Arnis",
    "Option2": "Sipa",
    "Option3": "Sepak Takraw",
    "Option4": "Kali",
    "Answer": "Sipa"
  },
  {
    "question_no.": 83,
    "Question": "What is the national sport of Canada besides ice hockey, a team sport played with a stick and a rubber ball on a field?",
    "Option1": "Football",
    "Option2": "Lacrosse",
    "Option3": "Basketball",
    "Option4": "Baseball",
    "Answer": "Lacrosse"
  },
  {
    "question_no.": 84,
    "Question": "In which country is 'Pehlwani', a traditional form of wrestling, deeply rooted in culture and sport?",
    "Option1": "Pakistan",
    "Option2": "Bangladesh",
    "Option3": "India",
    "Option4": "Nepal",
    "Answer": "India"
  },
  {
    "question_no.": 85,
    "Question": "What is the name of the traditional sport in Spain where a person attempts to dodge or vault over a bull without harming it?",
    "Option1": "Bullfighting",
    "Option2": "Recortes",
    "Option3": "Encierro",
    "Option4": "Jumping the Bull",
    "Answer": "Recortes"
  },
  {
    "question_no.": 86,
    "Question": "Which traditional sport from the Andean region of South America involves a form of ball game played with a heavy, rubber ball and gloved hands?",
    "Option1": "Pelota",
    "Option2": "Racquetry",
    "Option3": "Paleta",
    "Option4": "Fronton",
    "Answer": "Pelota"
  },
  {
    "question_no.": 87,
    "Question": "What is the national sport of Russia, a martial art that combines elements of judo, boxing, and wrestling?",
    "Option1": "Karate",
    "Option2": "Sambo",
    "Option3": "Judo",
    "Option4": "Wrestling",
    "Answer": "Sambo"
  },
  {
    "question_no.": 88,
    "Question": "In which country is 'Chovgan', a traditional polo-like game, considered a national sport?",
    "Option1": "Iran",
    "Option2": "Azerbaijan",
    "Option3": "Armenia",
    "Option4": "Turkey",
    "Answer": "Azerbaijan"
  },
  {
    "question_no.": 89,
    "Question": "What is the name of the traditional sport in Greenland, a form of Inuit wrestling where competitors try to throw each other over their heads?",
    "Option1": "Inuit Wrestling",
    "Option2": "Nutugkat",
    "Option3": "Greenland Games",
    "Option4": "Arctic Combat",
    "Answer": "Nutugkat"
  },
  {
    "question_no.": 90,
    "Question": "Which traditional sport from South Africa involves kicking a ball with the feet, a predecessor to modern football codes?",
    "Option1": "Rugby",
    "Option2": "Cricket",
    "Option3": "Diski",
    "Option4": "Soccer",
    "Answer": "Diski"
  },
  {
    "question_no.": 91,
    "Question": "What is the national sport of Finland, a bat-and-ball game often called 'Finnish Baseball'?",
    "Option1": "Pesäpallo",
    "Option2": "Lapta",
    "Option3": "Kyykkä",
    "Option4": "Mölkky",
    "Answer": "Pesäpallo"
  },
  {
    "question_no.": 92,
    "Question": "In which country is 'Fierljeppen', a traditional sport involving pole vaulting over canals, popular?",
    "Option1": "Germany",
    "Option2": "Belgium",
    "Option3": "Netherlands",
    "Option4": "Sweden",
    "Answer": "Netherlands"
  },
  {
    "question_no.": 93,
    "Question": "What is the name of the traditional sport in Mongolia that involves horse racing over long distances?",
    "Option1": "Naadam Horse Racing",
    "Option2": "Steppe Racing",
    "Option3": "Gobi Gallop",
    "Option4": "Nomadic Derby",
    "Answer": "Naadam Horse Racing"
  },
  {
    "question_no.": 94,
    "Question": "Which traditional sport from India involves a tag-like game played by two teams, where a 'chaser' tries to tag opponents while chanting 'kabaddi'?",
    "Option1": "Cricket",
    "Option2": "Kho Kho",
    "Option3": "Kabaddi",
    "Option4": "Gilli Danda",
    "Answer": "Kabaddi"
  },
  {
    "question_no.": 95,
    "Question": "What is the national sport of Saudi Arabia, a popular equestrian activity involving horse racing?",
    "Option1": "Polo",
    "Option2": "Endurance Riding",
    "Option3": "Camel Racing",
    "Option4": "Horse Racing",
    "Answer": "Horse Racing"
  },
  {
    "question_no.": 96,
    "Question": "In which country is 'Schwingen', a traditional form of wrestling where competitors wear canvas shorts and try to throw each other onto their backs, popular?",
    "Option1": "Austria",
    "Option2": "Germany",
    "Option3": "Switzerland",
    "Option4": "France",
    "Answer": "Switzerland"
  },
  {
    "question_no.": 97,
    "Question": "What is the name of the traditional sport in Japan where competitors aim to achieve spiritual and physical mastery through martial arts, involving various forms of self-defense?",
    "Option1": "Karate",
    "Option2": "Judo",
    "Option3": "Aikido",
    "Option4": "Kendo",
    "Answer": "Aikido"
  },
  {
    "question_no.": 98,
    "Question": "Which traditional sport from the Netherlands involves throwing a heavy, iron ball as far as possible?",
    "Option1": "Klootschieten",
    "Option2": "Fierljeppen",
    "Option3": "Boerengolf",
    "Option4": "Korfball",
    "Answer": "Klootschieten"
  },
  {
    "question_no.": 99,
    "Question": "What is the national sport of Thailand, a martial art known for its powerful kicking techniques?",
    "Option1": "Muay Boran",
    "Option2": "Muay Thai",
    "Option3": "Krabi-Krabong",
    "Option4": "Silat",
    "Answer": "Muay Thai"
  },
  {
    "question_no.": 100,
    "Question": "In which country is 'Wushu', a collection of Chinese martial arts forms, recognized as both a sport and an art form?",
    "Option1": "Japan",
    "Option2": "South Korea",
    "Option3": "China",
    "Option4": "Vietnam",
    "Answer": "China"
  },
  {
    "question_no.": 101,
    "Question": "What is the name of the traditional sport in India, particularly popular in rural areas, where two teams of nine players try to avoid being tagged by 'chasers'?",
    "Option1": "Kabaddi",
    "Option2": "Gilli Danda",
    "Option3": "Kho Kho",
    "Option4": "Lagori",
    "Answer": "Kho Kho"
  },
  {
    "question_no.": 102,
    "Question": "Which traditional sport from West Africa involves a form of wrestling often accompanied by drumming and chanting?",
    "Option1": "Dambe",
    "Option2": "Senegalese Wrestling (Laamb)",
    "Option3": "Edo Combat",
    "Option4": "Zulu Wrestling",
    "Answer": "Senegalese Wrestling (Laamb)"
  },
  {
    "question_no.": 103,
    "Question": "What is the national sport of Poland, a team sport played with a ball on a court with a net?",
    "Option1": "Football (Soccer)",
    "Option2": "Volleyball",
    "Option3": "Basketball",
    "Option4": "Handball",
    "Answer": "Volleyball"
  },
  {
    "question_no.": 104,
    "Question": "In which country is 'Lucha Canaria', a traditional form of wrestling with specific rules and holds, practiced?",
    "Option1": "Portugal",
    "Option2": "Spain (Canary Islands)",
    "Option3": "Morocco",
    "Option4": "Italy",
    "Answer": "Spain (Canary Islands)"
  },
  {
    "question_no.": 105,
    "Question": "What is the name of the traditional sport in Italy, particularly Venice, involving racing gondolas?",
    "Option1": "Regata Storica",
    "Option2": "Palio di Siena",
    "Option3": "Venetian Races",
    "Option4": "Gondola Derby",
    "Answer": "Regata Storica"
  },
  {
    "question_no.": 106,
    "Question": "Which traditional sport from the Middle East involves horseback riding skills and often includes picking up items from the ground while at a gallop?",
    "Option1": "Polo",
    "Option2": "Tent Pegging",
    "Option3": "Horse Archery",
    "Option4": "Jereed",
    "Answer": "Tent Pegging"
  },
  {
    "question_no.": 107,
    "Question": "What is the national sport of Afghanistan, a chaotic game played on horseback with a goat or calf carcass?",
    "Option1": "Polo",
    "Option2": "Buzkashi",
    "Option3": "Kokpar",
    "Option4": "Chovgan",
    "Answer": "Buzkashi"
  },
  {
    "question_no.": 108,
    "Question": "In which country is 'Naadam', an annual festival featuring traditional Mongolian sports, held?",
    "Option1": "Kazakhstan",
    "Option2": "Russia",
    "Option3": "Mongolia",
    "Option4": "China",
    "Answer": "Mongolia"
  },
  {
    "question_no.": 109,
    "Question": "What is the name of the traditional sport in Japan that involves a form of martial art focused on grappling and ground fighting?",
    "Option1": "Karate",
    "Option2": "Judo",
    "Option3": "Kendo",
    "Option4": "Aikido",
    "Answer": "Judo"
  },
  {
    "question_no.": 110,
    "Question": "Which traditional sport from the United States involves riding a wild bull for a set amount of time?",
    "Option1": "Bronc Riding",
    "Option2": "Bull Riding",
    "Option3": "Steer Wrestling",
    "Option4": "Calf Roping",
    "Answer": "Bull Riding"
  },
  {
    "question_no.": 111,
    "Question": "What is the national sport of Nepal, a team contact sport similar to Kabaddi?",
    "Option1": "Cricket",
    "Option2": "Dandi Biyo",
    "Option3": "Volleyball",
    "Option4": "Kabaddi",
    "Answer": "Volleyball"
  },
  {
    "question_no.": 112,
    "Question": "In which country is 'Kırkpınar', the oldest continuously run annual sports event in Turkey, featuring oil wrestling?",
    "Option1": "Greece",
    "Option2": "Bulgaria",
    "Option3": "Turkey",
    "Option4": "Iran",
    "Answer": "Turkey"
  },
  {
    "question_no.": 113,
    "Question": "What is the name of the traditional sport in Australia, particularly amongst Aboriginal communities, that involves throwing a boomerang?",
    "Option1": "Spear Throwing",
    "Option2": "Boomerang Throwing",
    "Option3": "Didgeridoo Competition",
    "Option4": "Aboriginal Cricket",
    "Answer": "Boomerang Throwing"
  },
  {
    "question_no.": 114,
    "Question": "Which traditional sport from Hungary involves horse archery, where riders shoot arrows while mounted?",
    "Option1": "Polo",
    "Option2": "Horse Archery",
    "Option3": "Tent Pegging",
    "Option4": "Jereed",
    "Answer": "Horse Archery"
  },
  {
    "question_no.": 115,
    "Question": "What is the national sport of Brazil, a martial art that combines elements of dance, acrobatics, and music?",
    "Option1": "Judo",
    "Option2": "Capoeira",
    "Option3": "Jiu-Jitsu",
    "Option4": "Samba",
    "Answer": "Capoeira"
  },
  {
    "question_no.": 116,
    "Question": "In which country is 'Bossaball', a dynamic sport played on an inflatable court with trampolines, gaining popularity?",
    "Option1": "Brazil",
    "Option2": "Spain",
    "Option3": "Portugal",
    "Option4": "Netherlands",
    "Answer": "Spain"
  },
  {
    "question_no.": 117,
    "Question": "What is the name of the traditional sport in Scotland that involves throwing a heavy hammer with a handle attached by a chain?",
    "Option1": "Caber Toss",
    "Option2": "Stone Put",
    "Option3": "Hammer Throw",
    "Option4": "Weight Over Bar",
    "Answer": "Hammer Throw"
  },
  {
    "question_no.": 118,
    "Question": "Which traditional sport from ancient Egypt involved wrestling and boxing, often depicted in tomb paintings?",
    "Option1": "Pankration",
    "Option2": "Egyptian Wrestling",
    "Option3": "Boxing",
    "Option4": "Gladiatorial Combat",
    "Answer": "Egyptian Wrestling"
  },
  {
    "question_no.": 119,
    "Question": "What is the national sport of Pakistan, a team sport played with sticks and a ball on a field?",
    "Option1": "Cricket",
    "Option2": "Badminton",
    "Option3": "Field Hockey",
    "Option4": "Squash",
    "Answer": "Field Hockey"
  },
  {
    "question_no.": 120,
    "Question": "In which country is 'Pato', a game played on horseback and considered a national sport, popular?",
    "Option1": "Chile",
    "Option2": "Uruguay",
    "Option3": "Argentina",
    "Option4": "Brazil",
    "Answer": "Argentina"
  },
  {
    "question_no.": 121,
    "Question": "What is the name of the traditional sport in the United Kingdom, particularly in rural communities, where competitors carry a heavy stone for distance or time?",
    "Option1": "Stone Carrying",
    "Option2": "Weightlifting",
    "Option3": "Atlas Stones",
    "Option4": "Highland Games",
    "Answer": "Stone Carrying"
  },
  {
    "question_no.": 122,
    "Question": "Which traditional sport from India involves hitting a small wooden peg (gilli) with a larger stick (danda)?",
    "Option1": "Cricket",
    "Option2": "Badminton",
    "Option3": "Gilli Danda",
    "Option4": "Kho Kho",
    "Answer": "Gilli Danda"
  },
  {
    "question_no.": 123,
    "Question": "What is the national sport of Sri Lanka, a team game played with a ball over a net, requiring players to hit it with their hands or fists?",
    "Option1": "Cricket",
    "Option2": "Football (Soccer)",
    "Option3": "Volleyball",
    "Option4": "Netball",
    "Answer": "Volleyball"
  },
  {
    "question_no.": 124,
    "Question": "In which country is 'Lath Mar Holi', a traditional stick-fighting celebration, practiced?",
    "Option1": "Pakistan",
    "Option2": "Bangladesh",
    "Option3": "India",
    "Option4": "Nepal",
    "Answer": "India"
  },
  {
    "question_no.": 125,
    "Question": "What is the name of the traditional sport in Indonesia, a martial art known for its diverse styles and emphasis on self-defense?",
    "Option1": "Karate",
    "Option2": "Silat",
    "Option3": "Muay Thai",
    "Option4": "Taekwondo",
    "Answer": "Silat"
  },
  {
    "question_no.": 126,
    "Question": "Which traditional sport from the Philippines involves sparring with sticks or bladed weapons?",
    "Option1": "Arnis / Eskrima / Kali",
    "Option2": "Sipa",
    "Option3": "Pencak Silat",
    "Option4": "Taekwondo",
    "Answer": "Arnis / Eskrima / Kali"
  },
  {
    "question_no.": 127,
    "Question": "What is the national sport of South Africa, a popular team sport played with an oval-shaped ball?",
    "Option1": "Soccer",
    "Option2": "Cricket",
    "Option3": "Rugby Union",
    "Option4": "Netball",
    "Answer": "Rugby Union"
  },
  {
    "question_no.": 128,
    "Question": "In which country is 'Jereed', an ancient Turkic equestrian sport, still performed in festivals?",
    "Option1": "Kazakhstan",
    "Option2": "Uzbekistan",
    "Option3": "Turkey",
    "Option4": "Azerbaijan",
    "Answer": "Turkey"
  },
  {
    "question_no.": 129,
    "Question": "What is the name of the traditional sport in France where players use mallets to hit a wooden ball through hoops on a grass court?",
    "Option1": "Petanque",
    "Option2": "Croquet",
    "Option3": "Boules",
    "Option4": "Bowling",
    "Answer": "Croquet"
  },
  {
    "question_no.": 130,
    "Question": "Which traditional sport from the Native American tribes involves using a stick with a net to catch and throw a ball, known as 'the Creators Game'?",
    "Option1": "Basketball",
    "Option2": "Lacrosse",
    "Option3": "Baseball",
    "Option4": "Football",
    "Answer": "Lacrosse"
  },
  {
    "question_no.": 131,
    "Question": "What is the national sport of New Zealand, a game played with an oval ball where teams try to score tries and conversions?",
    "Option1": "Soccer",
    "Option2": "Cricket",
    "Option3": "Rugby Union",
    "Option4": "Netball",
    "Answer": "Rugby Union"
  },
  {
    "question_no.": 132,
    "Question": "In which country is 'Varzesh-e Bastani', a traditional Iranian martial art, practiced in special gyms called 'Zurkhaneh'?",
    "Option1": "Afghanistan",
    "Option2": "Iraq",
    "Option3": "Iran",
    "Option4": "Pakistan",
    "Answer": "Iran"
  },
  {
    "question_no.": 133,
    "Question": "What is the name of the traditional sport in Mexico that involves a form of bullfighting where the bull is not killed?",
    "Option1": "Corrida de Toros",
    "Option2": "Jaripeo",
    "Option3": "Recortes",
    "Option4": "Charreria",
    "Answer": "Recortes"
  },
  {
    "question_no.": 134,
    "Question": "Which traditional sport from the Basque Country of Spain and France is played by hitting a ball against a wall with a specialized glove?",
    "Option1": "Pelota Vasca",
    "Option2": "Jai Alai",
    "Option3": "Fronton",
    "Option4": "Handball",
    "Answer": "Jai Alai"
  },
  {
    "question_no.": 135,
    "Question": "What is the national sport of Turkey, a form of wrestling where competitors are covered in olive oil?",
    "Option1": "Greco-Roman Wrestling",
    "Option2": "Oil Wrestling (Kırkpınar)",
    "Option3": "Freestyle Wrestling",
    "Option4": "Sambo",
    "Answer": "Oil Wrestling (Kırkpınar)"
  },
  {
    "question_no.": 136,
    "Question": "In which country is 'Ssirum', a traditional wrestling style where competitors grasp each other's 'satba' (cloth belts), popular?",
    "Option1": "Japan",
    "Option2": "China",
    "Option3": "South Korea",
    "Option4": "North Korea",
    "Answer": "South Korea"
  },
  {
    "question_no.": 137,
    "Question": "What is the name of the traditional sport in Egypt, a popular team sport played with a ball on a field with two goals?",
    "Option1": "Handball",
    "Option2": "Football (Soccer)",
    "Option3": "Volleyball",
    "Option4": "Basketball",
    "Answer": "Football (Soccer)"
  },
  {
    "question_no.": 138,
    "Question": "Which traditional sport from Central Asia involves horse racing, often over vast distances?",
    "Option1": "Buzkashi",
    "Option2": "Kokpar",
    "Option3": "Horse Racing",
    "Option4": "Horse Archery",
    "Answer": "Horse Racing"
  },
  {
    "question_no.": 139,
    "Question": "What is the national sport of Australia, a bat-and-ball game played between two teams of eleven players?",
    "Option1": "Rugby League",
    "Option2": "Australian Rules Football",
    "Option3": "Cricket",
    "Option4": "Soccer",
    "Answer": "Cricket"
  },
  {
    "question_no.": 140,
    "Question": "In which country is 'Paleta Fronton', a traditional racquet sport, widely played?",
    "Option1": "Argentina",
    "Option2": "Mexico",
    "Option3": "Peru",
    "Option4": "Chile",
    "Answer": "Peru"
  },
  {
    "question_no.": 141,
    "Question": "What is the name of the traditional sport in Scotland that involves throwing a heavy, spherical stone for distance?",
    "Option1": "Caber Toss",
    "Option2": "Stone Put",
    "Option3": "Hammer Throw",
    "Option4": "Shotput",
    "Answer": "Stone Put"
  },
  {
    "question_no.": 142,
    "Question": "Which traditional sport from ancient Rome involved combat between armed gladiators?",
    "Option1": "Chariot Racing",
    "Option2": "Gladiatorial Combat",
    "Option3": "Pankration",
    "Option4": "Olympic Games",
    "Answer": "Gladiatorial Combat"
  },
  {
    "question_no.": 143,
    "Question": "What is the national sport of China, a martial art known for its dynamic and acrobatic movements?",
    "Option1": "Karate",
    "Option2": "Judo",
    "Option3": "Wushu",
    "Option4": "Tai Chi",
    "Answer": "Wushu"
  },
  {
    "question_no.": 144,
    "Question": "In which country is 'Hornussen', a traditional team sport somewhat similar to baseball and golf, popular?",
    "Option1": "Germany",
    "Option2": "Austria",
    "Option3": "Switzerland",
    "Option4": "France",
    "Answer": "Switzerland"
  },
  {
    "question_no.": 145,
    "Question": "What is the name of the traditional sport in Brazil that involves a form of dance-like martial art, often performed in a 'roda' (circle)?",
    "Option1": "Samba",
    "Option2": "Capoeira",
    "Option3": "Jiu-Jitsu",
    "Option4": "Karate",
    "Answer": "Capoeira"
  },
  {
    "question_no.": 146,
    "Question": "Which traditional sport from the Arctic involves a form of hand-to-hand combat where opponents try to force each other to the ground?",
    "Option1": "Boxing",
    "Option2": "Wrestling",
    "Option3": "Inuit Boxing",
    "Option4": "Arm Wrestling",
    "Answer": "Inuit Boxing"
  },
  {
    "question_no.": 147,
    "Question": "What is the national sport of Vietnam, a martial art combining elements of traditional Vietnamese fighting styles?",
    "Option1": "Kung Fu",
    "Option2": "Vovinam",
    "Option3": "Taekwondo",
    "Option4": "Muay Thai",
    "Answer": "Vovinam"
  },
  {
    "question_no.": 148,
    "Question": "In which country is 'Dambe', a form of traditional boxing with one hand wrapped in cloth and rope, practiced?",
    "Option1": "Egypt",
    "Option2": "Nigeria",
    "Option3": "Ghana",
    "Option4": "Kenya",
    "Answer": "Nigeria"
  },
  {
    "question_no.": 149,
    "Question": "What is the name of the traditional sport in the United States, particularly popular in the South, that involves throwing a horse's horseshoe at a stake?",
    "Option1": "Bocce",
    "Option2": "Cornhole",
    "Option3": "Horseshoes",
    "Option4": "Bowling",
    "Answer": "Horseshoes"
  },
  {
    "question_no.": 150,
    "Question": "Which traditional sport from the Middle East involves horseback riders competing in throwing wooden javelins at a target?",
    "Option1": "Polo",
    "Option2": "Tent Pegging",
    "Option3": "Jereed",
    "Option4": "Horse Archery",
    "Answer": "Jereed"
  },
  {
    "question_no.": 151,
    "Question": "What is the national sport of Iceland, a form of wrestling characterized by a unique grip and throws?",
    "Option1": "Judo",
    "Option2": "Wrestling",
    "Option3": "Glima",
    "Option4": "Sumo",
    "Answer": "Glima"
  },
  {
    "question_no.": 152,
    "Question": "In which country is 'Korfball', a mixed-gender team sport somewhat similar to basketball and netball, popular?",
    "Option1": "Belgium",
    "Option2": "Netherlands",
    "Option3": "Germany",
    "Option4": "United Kingdom",
    "Answer": "Netherlands"
  },
  {
    "question_no.": 153,
    "Question": "What is the name of the traditional sport in Russia, a martial art that combines grappling and striking techniques, originally developed for military use?",
    "Option1": "Judo",
    "Option2": "Sambo",
    "Option3": "Karate",
    "Option4": "Boxing",
    "Answer": "Sambo"
  },
  {
    "question_no.": 154,
    "Question": "Which traditional sport from the Caucasus region involves a form of belt wrestling, where competitors hold onto each other's belts?",
    "Option1": "Chidaoba",
    "Option2": "Kuresh",
    "Option3": "Sambo",
    "Option4": "Judo",
    "Answer": "Kuresh"
  },
  {
    "question_no.": 155,
    "Question": "What is the national sport of Bangladesh, a contact team sport where a 'raider' tries to tag opponents in their territory and return to their own half?",
    "Option1": "Cricket",
    "Option2": "Football (Soccer)",
    "Option3": "Kabaddi",
    "Option4": "Field Hockey",
    "Answer": "Kabaddi"
  },
  {
    "question_no.": 156,
    "Question": "In which country is 'Dragon Boat Racing', a traditional paddling sport, a significant cultural event?",
    "Option1": "Japan",
    "Option2": "South Korea",
    "Option3": "China",
    "Option4": "Vietnam",
    "Answer": "China"
  },
  {
    "question_no.": 157,
    "Question": "What is the name of the traditional sport in Italy where two teams compete in a violent and chaotic form of football in a sand-filled piazza?",
    "Option1": "Roman Football",
    "Option2": "Calcio Storico Fiorentino",
    "Option3": "Palio di Siena",
    "Option4": "Bocce",
    "Answer": "Calcio Storico Fiorentino"
  },
  {
    "question_no.": 158,
    "Question": "Which traditional sport from the United Kingdom involves competitors racing while carrying a wife or partner over obstacles?",
    "Option1": "Wife Carrying",
    "Option2": "Husband Hurdling",
    "Option3": "Couples Obstacle Race",
    "Option4": "Relay Race",
    "Answer": "Wife Carrying"
  },
  {
    "question_no.": 159,
    "Question": "What is the national sport of Bhutan, a traditional form of archery practiced with specific rituals?",
    "Option1": "Druk-yul Archery",
    "Option2": "Bhutani Archery",
    "Option3": "Traditional Archery",
    "Option4": "Compound Archery",
    "Answer": "Traditional Archery"
  },
  {
    "question_no.": 160,
    "Question": "In which country is 'Pehlwani', a traditional form of wrestling practiced in an 'akhara' (wrestling arena), popular?",
    "Option1": "Pakistan",
    "Option2": "Bangladesh",
    "Option3": "India",
    "Option4": "Sri Lanka",
    "Answer": "India"
  },
  {
    "question_no.": 161,
    "Question": "What is the name of the traditional sport in Scotland that involves throwing a heavy weight over a bar using one hand?",
    "Option1": "Hammer Throw",
    "Option2": "Stone Put",
    "Option3": "Weight Over Bar",
    "Option4": "Caber Toss",
    "Answer": "Weight Over Bar"
  },
  {
    "question_no.": 162,
    "Question": "Which traditional sport from ancient Greece involved long-distance running in armor?",
    "Option1": "Marathon",
    "Option2": "Hoplitodromos (Race in Armor)",
    "Option3": "Pentathlon",
    "Option4": "Stadion Race",
    "Answer": "Hoplitodromos (Race in Armor)"
  },
  {
    "question_no.": 163,
    "Question": "What is the national sport of South Korea, a martial art known for its powerful kicks and self-defense techniques?",
    "Option1": "Karate",
    "Option2": "Judo",
    "Option3": "Taekwondo",
    "Option4": "Hapkido",
    "Answer": "Taekwondo"
  },
  {
    "question_no.": 164,
    "Question": "In which country is 'Charreada', a national sport and equestrian tradition, deeply ingrained in its culture?",
    "Option1": "Spain",
    "Option2": "Mexico",
    "Option3": "Argentina",
    "Option4": "USA",
    "Answer": "Mexico"
  },
  {
    "question_no.": 165,
    "Question": "What is the name of the traditional sport in England where participants roll cheese down a steep hill and chase after it?",
    "Option1": "Gloucester Cheese Roll",
    "Option2": "Cheese Rolling Festival",
    "Option3": "Cotswold Cheese Chase",
    "Option4": "Rural Cheese Race",
    "Answer": "Gloucester Cheese Roll"
  },
  {
    "question_no.": 166,
    "Question": "Which traditional sport from the Middle East involves equestrian skills and often includes picking up small objects from the ground while on horseback?",
    "Option1": "Polo",
    "Option2": "Tent Pegging",
    "Option3": "Jereed",
    "Option4": "Horse Archery",
    "Answer": "Tent Pegging"
  },
  {
    "question_no.": 167,
    "Question": "What is the national sport of Argentina, a game played on horseback with a ball and sticks?",
    "Option1": "Polo",
    "Option2": "Pato",
    "Option3": "Horseball",
    "Option4": "Rugby",
    "Answer": "Pato"
  },
  {
    "question_no.": 168,
    "Question": "In which country is 'Kaatsen' (Frisian Handball), a traditional bat-and-ball game, popular?",
    "Option1": "Germany",
    "Option2": "Belgium",
    "Option3": "Netherlands",
    "Option4": "France",
    "Answer": "Netherlands"
  },
  {
    "question_no.": 169,
    "Question": "What is the name of the traditional sport in Portugal where groups of 'forcados' try to stop a charging bull with their bare hands?",
    "Option1": "Corrida de Touros",
    "Option2": "Tourada",
    "Option3": "Forcados",
    "Option4": "Bull Leaping",
    "Answer": "Forcados"
  },
  {
    "question_no.": 170,
    "Question": "Which traditional sport from Iran involves a combination of wrestling, acrobatics, and strength exercises, performed in a 'Zurkhaneh'?",
    "Option1": "Wrestling",
    "Option2": "Varzesh-e Pahlavani",
    "Option3": "Judo",
    "Option4": "Karate",
    "Answer": "Varzesh-e Pahlavani"
  },
  {
    "question_no.": 171,
    "Question": "What is the national sport of Norway, a winter sport combining cross-country skiing and rifle shooting?",
    "Option1": "Ski Jumping",
    "Option2": "Alpine Skiing",
    "Option3": "Biathlon",
    "Option4": "Nordic Combined",
    "Answer": "Biathlon"
  },
  {
    "question_no.": 172,
    "Question": "In which country is 'Shinty', a traditional team sport with sticks and a ball, played?",
    "Option1": "Ireland",
    "Option2": "Scotland",
    "Option3": "Wales",
    "Option4": "England",
    "Answer": "Scotland"
  },
  {
    "question_no.": 173,
    "Question": "What is the name of the traditional sport in Japan that focuses on sword fighting with bamboo swords and protective armor?",
    "Option1": "Judo",
    "Option2": "Karate",
    "Option3": "Kendo",
    "Option4": "Aikido",
    "Answer": "Kendo"
  },
  {
    "question_no.": 174,
    "Question": "Which traditional sport from Central Asia involves horse-mounted players attempting to drag a goat carcass across a goal line?",
    "Option1": "Polo",
    "Option2": "Buzkashi",
    "Option3": "Kokpar",
    "Option4": "Chovgan",
    "Answer": "Kokpar"
  },
  {
    "question_no.": 175,
    "Question": "What is the national sport of New Zealand, a contact team sport played with an oval ball?",
    "Option1": "Soccer",
    "Option2": "Cricket",
    "Option3": "Rugby Union",
    "Option4": "Netball",
    "Answer": "Rugby Union"
  },
  {
    "question_no.": 176,
    "Question": "In which country is 'Chidaoba', a traditional Georgian wrestling style with no ground grappling, popular?",
    "Option1": "Armenia",
    "Option2": "Azerbaijan",
    "Option3": "Georgia",
    "Option4": "Russia",
    "Answer": "Georgia"
  },
  {
    "question_no.": 177,
    "Question": "What is the name of the traditional sport in the United States, particularly in rodeos, where a cowboy or cowgirl lassos a calf?",
    "Option1": "Bull Riding",
    "Option2": "Barrel Racing",
    "Option3": "Calf Roping",
    "Option4": "Steer Wrestling",
    "Answer": "Calf Roping"
  },
  {
    "question_no.": 178,
    "Question": "Which traditional sport from the Philippines involves kicking a 'sipa' (rattan ball) over a net with feet and head?",
    "Option1": "Arnis",
    "Option2": "Sipa",
    "Option3": "Sepak Takraw",
    "Option4": "Kali",
    "Answer": "Sipa"
  },
  {
    "question_no.": 179,
    "Question": "What is the national sport of Canada, a winter sport played on ice with sticks and a puck?",
    "Option1": "Lacrosse",
    "Option2": "Basketball",
    "Option3": "Ice Hockey",
    "Option4": "Curling",
    "Answer": "Ice Hockey"
  },
  {
    "question_no.": 180,
    "Question": "In which country is 'Gaelic Football', a blend of soccer and rugby, widely played and followed?",
    "Option1": "England",
    "Option2": "Scotland",
    "Option3": "Ireland",
    "Option4": "Wales",
    "Answer": "Ireland"
  },
  {
    "question_no.": 181,
    "Question": "What is the name of the traditional sport in Spain that involves an individual or team trying to evade a charging bull, often in a bullring?",
    "Option1": "Bullfighting",
    "Option2": "Running of the Bulls (Encierro)",
    "Option3": "Recortes",
    "Option4": "Jumping the Bull",
    "Answer": "Bullfighting"
  },
  {
    "question_no.": 182,
    "Question": "Which traditional sport from the Arctic regions involves races with dog-pulled sleds?",
    "Option1": "Cross-country skiing",
    "Option2": "Snowshoeing",
    "Option3": "Dog Sledding",
    "Option4": "Ice Fishing",
    "Answer": "Dog Sledding"
  },
  {
    "question_no.": 183,
    "Question": "What is the national sport of Mongolia, an equestrian sport where riders try to collect flags from the ground while on horseback?",
    "Option1": "Archery",
    "Option2": "Horse Racing",
    "Option3": "Horse Picking",
    "Option4": "Wrestling",
    "Answer": "Horse Picking"
  },
  {
    "question_no.": 184,
    "Question": "In which country is 'Arnis', a traditional Filipino martial art, the national sport and martial art?",
    "Option1": "Indonesia",
    "Option2": "Malaysia",
    "Option3": "Philippines",
    "Option4": "Thailand",
    "Answer": "Philippines"
  },
  {
    "question_no.": 185,
    "Question": "What is the name of the traditional sport in Thailand, a martial art known for its powerful use of shins and elbows?",
    "Option1": "Karate",
    "Option2": "Taekwondo",
    "Option3": "Muay Thai",
    "Option4": "Kung Fu",
    "Answer": "Muay Thai"
  },
  {
    "question_no.": 186,
    "Question": "Which traditional sport from the Canary Islands involves a form of wrestling where the objective is to throw the opponent out of a circular area?",
    "Option1": "Canarian Combat",
    "Option2": "Lucha Canaria",
    "Option3": "Island Wrestling",
    "Option4": "Tenerife Fight",
    "Answer": "Lucha Canaria"
  },
  {
    "question_no.": 187,
    "Question": "What is the national sport of Peru, a racquet sport played on a fronton court?",
    "Option1": "Tennis",
    "Option2": "Paleta Fronton",
    "Option3": "Badminton",
    "Option4": "Squash",
    "Answer": "Paleta Fronton"
  },
  {
    "question_no.": 188,
    "Question": "In which country is 'Pesäpallo', often called the 'Finnish national game', popular?",
    "Option1": "Sweden",
    "Option2": "Norway",
    "Option3": "Finland",
    "Option4": "Denmark",
    "Answer": "Finland"
  },
  {
    "question_no.": 189,
    "Question": "What is the name of the traditional sport in Mexico where charros (cowboys) perform various equestrian and roping skills?",
    "Option1": "Rodeo",
    "Option2": "Charreada",
    "Option3": "Jaripeo",
    "Option4": "Horse Racing",
    "Answer": "Charreada"
  },
  {
    "question_no.": 190,
    "Question": "Which traditional sport from South Africa involves kicking a ball with the feet, a traditional form of football?",
    "Option1": "Rugby",
    "Option2": "Cricket",
    "Option3": "Diski",
    "Option4": "Soccer",
    "Answer": "Diski"
  },
  {
    "question_no.": 191,
    "Question": "What is the national sport of Uruguay, a game played on horseback with a ball and sticks, where the ball is carried in a net?",
    "Option1": "Polo",
    "Option2": "Pato",
    "Option3": "Horseball",
    "Option4": "Hockey",
    "Answer": "Pato"
  },
  {
    "question_no.": 192,
    "Question": "In which country is 'Kulak Dzhog', a form of bare-knuckle fighting, a traditional sport?",
    "Option1": "Ukraine",
    "Option2": "Belarus",
    "Option3": "Russia",
    "Option4": "Kazakhstan",
    "Answer": "Russia"
  },
  {
    "question_no.": 193,
    "Question": "What is the name of the traditional sport in China that involves various styles of martial arts for both combat and performance?",
    "Option1": "Kung Fu",
    "Option2": "Wushu",
    "Option3": "Tai Chi",
    "Option4": "Shaolin Kung Fu",
    "Answer": "Wushu"
  },
  {
    "question_no.": 194,
    "Question": "Which traditional sport from India involves hitting a small wooden peg (gilli) with a larger wooden stick (danda)?",
    "Option1": "Cricket",
    "Option2": "Gilli Danda",
    "Option3": "Kho Kho",
    "Option4": "Lagori",
    "Answer": "Gilli Danda"
  },
  {
    "question_no.": 195,
    "Question": "What is the national sport of Sri Lanka, a team sport similar to volleyball where the ball is hit over a net with hands or fists?",
    "Option1": "Cricket",
    "Option2": "Badminton",
    "Option3": "Volleyball",
    "Option4": "Rugby",
    "Answer": "Volleyball"
  },
  {
    "question_no.": 196,
    "Question": "In which country is 'Fierljeppen', an athletic event where competitors use a long pole to cross ditches or canals, popular?",
    "Option1": "Germany",
    "Option2": "Belgium",
    "Option3": "Netherlands",
    "Option4": "Sweden",
    "Answer": "Netherlands"
  },
  {
    "question_no.": 197,
    "Question": "What is the name of the traditional sport in Italy that features historical parades and a violent football match?",
    "Option1": "Roman Games",
    "Option2": "Palio di Siena",
    "Option3": "Calcio Storico",
    "Option4": "Venetian Regatta",
    "Answer": "Calcio Storico"
  },
  {
    "question_no.": 198,
    "Question": "Which traditional sport from the Middle East involves horseback riding and often includes picking up items from the ground with a lance?",
    "Option1": "Polo",
    "Option2": "Tent Pegging",
    "Option3": "Jereed",
    "Option4": "Horse Archery",
    "Answer": "Tent Pegging"
  },
  {
    "question_no.": 199,
    "Question": "What is the national sport of Scotland, a team sport played with sticks and a ball, similar to hurling but with different rules?",
    "Option1": "Football",
    "Option2": "Golf",
    "Option3": "Shinty",
    "Option4": "Curling",
    "Answer": "Shinty"
  },
  {
    "question_no.": 200,
    "Question": "In which country is 'Sambo', a martial art and combat sport, a national sport?",
    "Option1": "Ukraine",
    "Option2": "Belarus",
    "Option3": "Russia",
    "Option4": "Kazakhstan",
    "Answer": "Russia"
  },
  {
    "question_no.": 201,
    "Question": "What is the name of the traditional sport in the Philippines where individuals practice weapon-based fighting with sticks, knives, and bare hands?",
    "Option1": "Silat",
    "Option2": "Arnis",
    "Option3": "Muay Thai",
    "Option4": "Taekwondo",
    "Answer": "Arnis"
  },
  {
    "question_no.": 202,
    "Question": "Which traditional sport from Central Asia involves horse-mounted wrestling with a sheep or goat carcass?",
    "Option1": "Buzkashi",
    "Option2": "Kokpar",
    "Option3": "Chovgan",
    "Option4": "Polo",
    "Answer": "Kokpar"
  },
  {
    "question_no.": 203,
    "Question": "What is the national sport of Canada, a team sport played with a stick and a ball, often called 'the fastest game on two feet'?",
    "Option1": "Ice Hockey",
    "Option2": "Basketball",
    "Option3": "Lacrosse",
    "Option4": "Baseball",
    "Answer": "Lacrosse"
  },
  {
    "question_no.": 204,
    "Question": "In which country is 'Gaelic Football', a unique field sport combining elements of soccer and rugby, immensely popular?",
    "Option1": "Scotland",
    "Option2": "England",
    "Option3": "Ireland",
    "Option4": "Wales",
    "Answer": "Ireland"
  },
  {
    "question_no.": 205,
    "Question": "What is the name of the traditional sport in Afghanistan where horsemen compete to seize a goat or calf carcass and carry it to a scoring area?",
    "Option1": "Polo",
    "Option2": "Buzkashi",
    "Option3": "Chovgan",
    "Option4": "Jereed",
    "Answer": "Buzkashi"
  }
]