[
  {
    "word_no.": 1,
    "word": "ACCRETION",
    "hints": [
      "The process of growth or increase, typically by the gradual accumulation of additional layers or matter.",
      "A process by which material is added to a tectonic plate or a landmass.",
      "The gradual buildup of continents through geologic processes."
    ]
  },
  {
    "word_no.": 2,
    "word": "ANICLINE",
    "hints": [
      "A type of fold in rock layers that is convex upward, like a capital 'A'.",
      "The upward-arching part of a fold.",
      "Geological structure where rock layers dip away from a central axis."
    ]
  },
  {
    "word_no.": 3,
    "word": "ARCHIPELAGO",
    "hints": [
      "A group or chain of islands clustered together in a sea or ocean.",
      "Hawaii is an example of this.",
      "Often volcanic in origin."
    ]
  },
  {
    "word_no.": 4,
    "word": "BASALT",
    "hints": [
      "A fine-grained, dark-colored igneous rock.",
      "The most common rock type in the Earth's oceanic crust.",
      "Forms from the rapid cooling of lava."
    ]
  },
  {
    "word_no.": 5,
    "word": "CALDERA",
    "hints": [
      "A large, cauldron-like hollow that forms shortly after the emptying of a magma chamber.",
      "Often forms after a volcanic eruption.",
      "Crater Lake in Oregon is a famous example."
    ]
  },
  {
    "word_no.": 6,
    "word": "CANYON",
    "hints": [
      "A deep, narrow valley with steep sides.",
      "Often carved by a river over millions of years.",
      "The Grand Canyon is the most famous example."
    ]
  },
  {
    "word_no.": 7,
    "word": "CLAY",
    "hints": [
      "A fine-grained natural rock or soil material.",
      "Becomes plastic when wet.",
      "Used to make pottery and bricks."
    ]
  },
  {
    "word_no.": 8,
    "word": "CONGLOMERATE",
    "hints": [
      "A coarse-grained sedimentary rock.",
      "Composed of rounded gravel and cobbles.",
      "Looks like a mixture of smaller rocks cemented together."
    ]
  },
  {
    "word_no.": 9,
    "word": "CONTINENTAL DRIFT",
    "hints": [
      "The theory that the Earth's continents have moved over geologic time.",
      "Proposed by Alfred Wegener.",
      "A precursor to plate tectonics."
    ]
  },
  {
    "word_no.": 10,
    "word": "CORE",
    "hints": [
      "The innermost layer of the Earth.",
      "Made up primarily of iron and nickel.",
      "Divided into an inner and outer section."
    ]
  },
  {
    "word_no.": 11,
    "word": "CRATER",
    "hints": [
      "A large bowl-shaped depression.",
      "Can be formed by a meteorite impact or a volcanic eruption.",
      "Mount St. Helens has a prominent one."
    ]
  },
  {
    "word_no.": 12,
    "word": "CRUST",
    "hints": [
      "The outermost solid shell of a rocky planet.",
      "Divided into oceanic and continental types.",
      "The layer of Earth we live on."
    ]
  },
  {
    "word_no.": 13,
    "word": "DELTA",
    "hints": [
      "A landform created by deposition of sediment at the mouth of a river.",
      "Often triangular in shape.",
      "The Mississippi River has a famous one."
    ]
  },
  {
    "word_no.": 14,
    "word": "DIAGENESIS",
    "hints": [
      "The physical and chemical changes that turn sediment into rock.",
      "Includes compaction and cementation.",
      "A process that occurs after deposition."
    ]
  },
  {
    "word_no.": 15,
    "word": "DIORITE",
    "hints": [
      "A coarse-grained intrusive igneous rock.",
      "Intermediate in composition between granite and gabbro.",
      "Composed of plagioclase feldspar, hornblende, and biotite."
    ]
  },
  {
    "word_no.": 16,
    "word": "DIKE",
    "hints": [
      "A sheet of rock that is formed in a fracture in a pre-existing rock body.",
      "Often cuts across layers of older rock.",
      "A type of intrusive igneous rock formation."
    ]
  },
  {
    "word_no.": 17,
    "word": "DOLOMITE",
    "hints": [
      "A type of carbonate rock and a mineral.",
      "A common mineral in the sedimentary rock called dolostone.",
      "Often forms from the alteration of limestone."
    ]
  },
  {
    "word_no.": 18,
    "word": "EROSION",
    "hints": [
      "The geological process in which earthen materials are worn away.",
      "Caused by wind, water, or ice.",
      "The wearing away of the land."
    ]
  },
  {
    "word_no.": 19,
    "word": "FAULT",
    "hints": [
      "A fracture in rock where there has been movement and displacement.",
      "The San Andreas is a famous example.",
      "Causes earthquakes."
    ]
  },
  {
    "word_no.": 20,
    "word": "FELDSPAR",
    "hints": [
      "A group of rock-forming tectosilicate minerals.",
      "Makes up about 60% of the Earth's crust.",
      "A major component of igneous rocks."
    ]
  },
  {
    "word_no.": 21,
    "word": "FJORD",
    "hints": [
      "A long, narrow inlet with steep sides.",
      "Carved by glacial activity.",
      "Common in Norway and New Zealand."
    ]
  },
  {
    "word_no.": 22,
    "word": "FOSSIL",
    "hints": [
      "The preserved remains or traces of ancient life.",
      "Can be found in sedimentary rock.",
      "Evidence of past life on Earth."
    ]
  },
  {
    "word_no.": 23,
    "word": "GABBRO",
    "hints": [
      "A coarse-grained intrusive igneous rock.",
      "Compositionally equivalent to basalt.",
      "A key component of the lower oceanic crust."
    ]
  },
  {
    "word_no.": 24,
    "word": "GNEISS",
    "hints": [
      "A foliated metamorphic rock.",
      "Characterized by alternating bands of light and dark minerals.",
      "Forms from the metamorphism of granite."
    ]
  },
  {
    "word_no.": 25,
    "word": "GRANITE",
    "hints": [
      "A coarse-grained intrusive igneous rock.",
      "Forms from slowly cooling magma.",
      "Commonly used in countertops."
    ]
  },
  {
    "word_no.": 26,
    "word": "HOTSPOT",
    "hints": [
      "An area of volcanic activity away from plate boundaries.",
      "Responsible for the formation of the Hawaiian Islands.",
      "Caused by an upwelling of magma from the mantle."
    ]
  },
  {
    "word_no.": 27,
    "word": "IGNEOUS",
    "hints": [
      "One of the three main rock types.",
      "Formed from the cooling and solidification of molten rock.",
      "Comes from the Latin word for 'fire'."
    ]
  },
  {
    "word_no.": 28,
    "word": "JURASSIC",
    "hints": [
      "A period of the Mesozoic Era.",
      "Known as the 'Age of Dinosaurs'.",
      "Came after the Triassic Period."
    ]
  },
  {
    "word_no.": 29,
    "word": "LAVA",
    "hints": [
      "Molten rock that has erupted onto the Earth's surface.",
      "A source of igneous rock.",
      "What magma is called when it's above ground."
    ]
  },
  {
    "word_no.": 30,
    "word": "LIMESTONE",
    "hints": [
      "A sedimentary rock composed mainly of calcium carbonate.",
      "Often contains fossils.",
      "The primary rock type of many caves."
    ]
  },
  {
    "word_no.": 31,
    "word": "LITHOSPHERE",
    "hints": [
      "The rigid outermost shell of a rocky planet.",
      "Includes the crust and the uppermost mantle.",
      "It is broken into tectonic plates."
    ]
  },
  {
    "word_no.": 32,
    "word": "MAGMA",
    "hints": [
      "Molten rock found beneath the Earth's surface.",
      "Source of igneous rock.",
      "Erupts to become lava."
    ]
  },
  {
    "word_no.": 33,
    "word": "MANTLE",
    "hints": [
      "The layer of the Earth between the crust and the core.",
      "Makes up most of the Earth's volume.",
      "Where convection currents drive plate tectonics."
    ]
  },
  {
    "word_no.": 34,
    "word": "MARBLE",
    "hints": [
      "A metamorphic rock composed of recrystallized carbonate minerals.",
      "Often used in sculpture and architecture.",
      "Forms from the metamorphism of limestone."
    ]
  },
  {
    "word_no.": 35,
    "word": "METAMORPHIC",
    "hints": [
      "One of the three main rock types.",
      "Formed from existing rock subjected to heat and pressure.",
      "Examples include marble and slate."
    ]
  },
  {
    "word_no.": 36,
    "word": "MINERAL",
    "hints": [
      "A naturally occurring, inorganic solid with a specific chemical composition.",
      "The building blocks of rocks.",
      "Quartz and mica are examples."
    ]
  },
  {
    "word_no.": 37,
    "word": "MORANE",
    "hints": [
      "Accumulated debris and sediment carried by a glacier.",
      "Can form a ridge or mound.",
      "Evidence of past glaciation."
    ]
  },
  {
    "word_no.": 38,
    "word": "OBSIDIAN",
    "hints": [
      "A naturally occurring volcanic glass.",
      "Forms from very rapid cooling of lava.",
      "Often black and smooth."
    ]
  },
  {
    "word_no.": 39,
    "word": "ORE",
    "hints": [
      "A type of rock that contains valuable minerals.",
      "Often contains metals like gold, silver, or copper.",
      "Mined for economic purposes."
    ]
  },
  {
    "word_no.": 40,
    "word": "OROGENY",
    "hints": [
      "The process of mountain formation.",
      "Caused by plate tectonics.",
      "The collision of continents leads to this."
    ]
  },
  {
    "word_no.": 41,
    "word": "PALEONTOLOGY",
    "hints": [
      "The scientific study of life that existed in past geologic periods.",
      "Involves the study of fossils.",
      "A sub-discipline of geology."
    ]
  },
  {
    "word_no.": 42,
    "word": "PUMICE",
    "hints": [
      "A type of volcanic rock that is very light and porous.",
      "Forms when super-heated, highly pressurized rock is ejected from a volcano.",
      "Can float on water."
    ]
  },
  {
    "word_no.": 43,
    "word": "QUARTZ",
    "hints": [
      "One of the most abundant minerals in the Earth's continental crust.",
      "Hard and crystalline.",
      "Found in many types of rocks, including granite."
    ]
  },
  {
    "word_no.": 44,
    "word": "RIFT",
    "hints": [
      "A major fracture in the Earth's crust.",
      "Often where new crust is being formed.",
      "The East African ___ Valley is a famous example."
    ]
  },
  {
    "word_no.": 45,
    "word": "ROCK CYCLE",
    "hints": [
      "The continuous process by which rocks are created, changed, and destroyed.",
      "Describes how igneous, sedimentary, and metamorphic rocks are related.",
      "Involves processes like weathering, erosion, and metamorphism."
    ]
  },
  {
    "word_no.": 46,
    "word": "SANDSTONE",
    "hints": [
      "A clastic sedimentary rock composed mainly of sand-sized mineral particles.",
      "Often red or brown in color.",
      "Forms in deserts, rivers, and oceans."
    ]
  },
  {
    "word_no.": 47,
    "word": "SCHIST",
    "hints": [
      "A medium-grade metamorphic rock.",
      "Contains platy mineral grains like mica.",
      "Characterized by its foliation."
    ]
  },
  {
    "word_no.": 48,
    "word": "SEDIMENT",
    "hints": [
      "Particulate matter that is transported by wind, water, or ice.",
      "Deposition of this material leads to the formation of sedimentary rock.",
      "Sand and silt are examples."
    ]
  },
  {
    "word_no.": 49,
    "word": "SEDIMENTARY",
    "hints": [
      "One of the three main rock types.",
      "Formed from the deposition and cementation of material at the Earth's surface.",
      "Examples include sandstone and shale."
    ]
  },
  {
    "word_no.": 50,
    "word": "SEISMIC WAVE",
    "hints": [
      "An elastic wave generated by an impulse like an earthquake.",
      "Types include P-waves and S-waves.",
      "Travels through the Earth's interior."
    ]
  },
  {
    "word_no.": 51,
    "word": "SHALE",
    "hints": [
      "A fine-grained sedimentary rock.",
      "Composed of mud that is a mix of clay minerals and tiny fragments.",
      "Often has a layered appearance."
    ]
  },
  {
    "word_no.": 52,
    "word": "SLATE",
    "hints": [
      "A fine-grained, foliated metamorphic rock.",
      "Formed from the metamorphism of shale.",
      "Often used for roofing tiles."
    ]
  },
  {
    "word_no.": 53,
    "word": "STRATIGRAPHY",
    "hints": [
      "A branch of geology concerned with the study of rock layers.",
      "Helps determine the relative age of rocks.",
      "The study of strata."
    ]
  },
  {
    "word_no.": 54,
    "word": "SUBDUCTION",
    "hints": [
      "The process where one tectonic plate moves under another.",
      "Occurs at convergent plate boundaries.",
      "Associated with deep ocean trenches and volcanic arcs."
    ]
  },
  {
    "word_no.": 55,
    "word": "SYNCLINE",
    "hints": [
      "A type of fold in rock layers that is concave upward, like a smile.",
      "The downward-curving part of a fold.",
      "The opposite of an anticline."
    ]
  },
  {
    "word_no.": 56,
    "word": "TECTONICS",
    "hints": [
      "The study of the processes that control the structure and properties of the Earth's crust.",
      "Relates to the movement of large plates.",
      "The force that drives continental drift."
    ]
  },
  {
    "word_no.": 57,
    "word": "TRENCH",
    "hints": [
      "A long, narrow depression in the ocean floor.",
      "Formed at a subduction zone.",
      "The deepest parts of the ocean."
    ]
  },
  {
    "word_no.": 58,
    "word": "VOLCANO",
    "hints": [
      "A rupture in the crust of a planetary-mass object.",
      "Allows hot lava, volcanic ash, and gases to escape.",
      "Mount Vesuvius is a famous example."
    ]
  },
  {
    "word_no.": 59,
    "word": "WEATHERING",
    "hints": [
      "The breaking down of rocks, soil, and minerals.",
      "Caused by contact with the atmosphere, water, and biological organisms.",
      "Can be physical, chemical, or biological."
    ]
  },
  {
    "word_no.": 60,
    "word": "GEYSER",
    "hints": [
      "A rare type of hot spring that is under pressure and erupts.",
      "Old Faithful is a very well-known example.",
      "Found in volcanic areas."
    ]
  },
  {
    "word_no.": 61,
    "word": "GLACIER",
    "hints": [
      "A persistent body of dense ice that is constantly moving.",
      "Formed from compressed snow.",
      "Carves U-shaped valleys."
    ]
  },
  {
    "word_no.": 62,
    "word": "HALITE",
    "hints": [
      "The mineral form of sodium chloride.",
      "Commonly known as rock salt.",
      "Often forms in evaporite deposits."
    ]
  },
  {
    "word_no.": 63,
    "word": "HEMATITE",
    "hints": [
      "A common iron oxide mineral.",
      "The principal source of iron ore.",
      "Can be red, black, or silver."
    ]
  },
  {
    "word_no.": 64,
    "word": "LIGNITE",
    "hints": [
      "A soft, brown, combustible sedimentary rock.",
      "A low-grade form of coal.",
      "Often referred to as 'brown coal'."
    ]
  },
  {
    "word_no.": 65,
    "word": "LOESS",
    "hints": [
      "A fine, wind-deposited silt.",
      "Forms fertile soil.",
      "Found in large deposits in China and the American Midwest."
    ]
  },
  {
    "word_no.": 66,
    "word": "MICA",
    "hints": [
      "A group of sheet silicate minerals.",
      "Known for its perfect cleavage, forming thin, flaky layers.",
      "A key component in granite."
    ]
  },
  {
    "word_no.": 67,
    "word": "MOLEHILL",
    "hints": [
      "A conical mound of earth raised by a small, burrowing animal.",
      "A small, hummock-like landform.",
      "A common sight in lawns and fields."
    ]
  },
  {
    "word_no.": 68,
    "word": "OBSIDIAN",
    "hints": [
      "A naturally occurring volcanic glass.",
      "Forms from the rapid cooling of lava.",
      "Black and shiny with a sharp edge."
    ]
  },
  {
    "word_no.": 69,
    "word": "PERMAFROST",
    "hints": [
      "Ground that remains completely frozen for two or more consecutive years.",
      "Found in polar and high-altitude regions.",
      "Thawing of this can release greenhouse gases."
    ]
  },
  {
    "word_no.": 70,
    "word": "PETROLOGY",
    "hints": [
      "The branch of geology that studies rocks and the conditions under which they form.",
      "A sub-discipline of geology.",
      "The study of rocks."
    ]
  },
  {
    "word_no.": 71,
    "word": "PLATEAU",
    "hints": [
      "A large, high-level area of flat or gently rolling land.",
      "Also known as a tableland.",
      "The Tibetan one is the world's highest and largest."
    ]
  },
  {
    "word_no.": 72,
    "word": "PLATINUM",
    "hints": [
      "A dense, malleable, ductile, highly unreactive precious metal.",
      "A rare element in the Earth's crust.",
      "Used in jewelry and catalytic converters."
    ]
  },
  {
    "word_no.": 73,
    "word": "PLUTON",
    "hints": [
      "A body of intrusive igneous rock.",
      "Forms when magma solidifies underground.",
      "The core of a mountain range can be this."
    ]
  },
  {
    "word_no.": 74,
    "word": "PORPHYRY",
    "hints": [
      "A textural term for an igneous rock with large crystals in a fine-grained matrix.",
      "Often used to describe a type of mineral deposit.",
      "Looks like a 'rock with freckles'."
    ]
  },
  {
    "word_no.": 75,
    "word": "PYRITE",
    "hints": [
      "An iron sulfide mineral.",
      "Also known as 'fool's gold'.",
      "Has a metallic luster and a brassy-yellow hue."
    ]
  },
  {
    "word_no.": 76,
    "word": "REFRACTIVE INDEX",
    "hints": [
      "A measure of the bending of a ray of light when passing from one medium into another.",
      "A key property for identifying minerals.",
      "A value that determines how much a substance will slow down light."
    ]
  },
  {
    "word_no.": 77,
    "word": "SADIM",
    "hints": [
      "An informal term for a depression formed by melting of buried ice.",
      "Can be found in glacial outwash plains.",
      "A type of geological formation."
    ]
  },
  {
    "word_no.": 78,
    "word": "SCHIST",
    "hints": [
      "A medium-grade metamorphic rock.",
      "Often contains abundant mica.",
      "Has a characteristic layered appearance."
    ]
  },
  {
    "word_no.": 79,
    "word": "SULFIDE",
    "hints": [
      "A compound containing the sulfide ion, $S^2$.",
      "A common type of mineral, including pyrite.",
      "Often an important ore of metals."
    ]
  },
  {
    "word_no.": 80,
    "word": "SILT",
    "hints": [
      "A granular material of a size between sand and clay.",
      "Often found in riverbeds and deltas.",
      "Deposited by water or wind."
    ]
  },
  {
    "word_no.": 81,
    "word": "SINKHOLE",
    "hints": [
      "A depression or hole in the ground.",
      "Caused by the collapse of the surface layer.",
      "Common in areas with soluble rocks like limestone."
    ]
  },
  {
    "word_no.": 82,
    "word": "STALACTITE",
    "hints": [
      "An icicle-shaped formation hanging from the ceiling of a cave.",
      "Formed by the dripping of mineral-rich water.",
      "Often found with its counterpart on the floor."
    ]
  },
  {
    "word_no.": 83,
    "word": "STALAGMITE",
    "hints": [
      "An upward-growing formation on the floor of a cave.",
      "Formed by mineral deposits from dripping water.",
      "The opposite of a stalactite."
    ]
  },
  {
    "word_no.": 84,
    "word": "TALC",
    "hints": [
      "A mineral with a monoclinic crystal structure.",
      "The softest mineral on the Mohs scale.",
      "Often used in cosmetics and baby powder."
    ]
  },
  {
    "word_no.": 85,
    "word": "TEPHRA",
    "hints": [
      "Fragmental material produced by a volcanic eruption.",
      "Includes volcanic ash, lapilli, and bombs.",
      "A general term for volcanic ejecta."
    ]
  },
  {
    "word_no.": 86,
    "word": "TOPAZ",
    "hints": [
      "A silicate mineral of aluminum and fluorine.",
      "A popular gemstone.",
      "The birthstone for November."
    ]
  },
  {
    "word_no.": 87,
    "word": "TUFF",
    "hints": [
      "A rock composed of volcanic ash and fragmented rock.",
      "Formed during a volcanic eruption.",
      "A type of igneous rock."
    ]
  },
  {
    "word_no.": 88,
    "word": "UNCONFORMITY",
    "hints": [
      "A buried erosional or non-depositional surface.",
      "Represents a gap in the geologic record.",
      "A break in the deposition of sedimentary rock layers."
    ]
  },
  {
    "word_no.": 89,
    "word": "VEIN",
    "hints": [
      "A sheetlike body of crystallized minerals.",
      "Forms in a fracture or joint in a rock.",
      "Often where precious metals like gold are found."
    ]
  },
  {
    "word_no.": 90,
    "word": "VOLCANIC NECK",
    "hints": [
      "The central plug of a volcano.",
      "Forms when magma solidifies within the vent.",
      "Shiprock in New Mexico is a famous example."
    ]
  },
  {
    "word_no.": 91,
    "word": "WEGENER",
    "hints": [
      "German geophysicist and meteorologist.",
      "Proposed the theory of continental drift.",
      "His theory was initially dismissed by the scientific community."
    ]
  },
  {
    "word_no.": 92,
    "word": "ZIRCON",
    "hints": [
      "A mineral of zirconium silicate.",
      "One of the oldest minerals on Earth.",
      "Used for radiometric dating."
    ]
  },
  {
    "word_no.": 93,
    "word": "CALCITE",
    "hints": [
      "A carbonate mineral and the most stable polymorph of calcium carbonate.",
      "Primary component of limestone.",
      "Has a distinctive rhombohedral cleavage."
    ]
  },
  {
    "word_no.": 94,
    "word": "CHERT",
    "hints": [
      "A hard, fine-grained sedimentary rock.",
      "Composed of microcrystalline or cryptocrystalline quartz.",
      "Used by ancient peoples to make stone tools."
    ]
  },
  {
    "word_no.": 95,
    "word": "COAL",
    "hints": [
      "A combustible black or brownish-black sedimentary rock.",
      "Formed from the remains of plants.",
      "A major source of energy."
    ]
  },
  {
    "word_no.": 96,
    "word": "CORUNDUM",
    "hints": [
      "A crystalline form of aluminum oxide.",
      "The mineral that gives us rubies and sapphires.",
      "The second hardest mineral on the Mohs scale."
    ]
  },
  {
    "word_no.": 97,
    "word": "DIAMOND",
    "hints": [
      "A solid form of pure carbon.",
      "The hardest known natural mineral.",
      "A valuable gemstone."
    ]
  },
  {
    "word_no.": 98,
    "word": "DOLINE",
    "hints": [
      "A closed depression draining underground.",
      "The most common form of a sinkhole.",
      "Found in karst landscapes."
    ]
  },
  {
    "word_no.": 99,
    "word": "EPICENTER",
    "hints": [
      "The point on the Earth's surface directly above the focus of an earthquake.",
      "Where the seismic waves are often strongest.",
      "Determined by seismographs."
    ]
  },
  {
    "word_no.": 100,
    "word": "ESKER",
    "hints": [
      "A long, winding ridge of stratified sand and gravel.",
      "Deposited by meltwater streams flowing within or under a glacier.",
      "Evidence of past glacial activity."
    ]
  },
  {
    "word_no.": 101,
    "word": "FLOODPLAIN",
    "hints": [
      "A flat area of land next to a river.",
      "Formed by the deposition of sediment during floods.",
      "Often very fertile soil."
    ]
  },
  {
    "word_no.": 102,
    "word": "FOLIATION",
    "hints": [
      "The planar arrangement of structural features in a metamorphic rock.",
      "Creates a layered or banded appearance.",
      "Seen in rocks like slate and schist."
    ]
  },
  {
    "word_no.": 103,
    "word": "GEMSTONE",
    "hints": [
      "A piece of mineral crystal that is cut and polished.",
      "Used to make jewelry and other ornaments.",
      "Rubies, emeralds, and sapphires are examples."
    ]
  },
  {
    "word_no.": 104,
    "word": "GEODE",
    "hints": [
      "A rock cavity lined with crystals.",
      "Often spherical or ovoid in shape.",
      "Hollow inside with a sparkling interior."
    ]
  },
  {
    "word_no.": 105,
    "word": "GLACIAL TILL",
    "hints": [
      "Unsorted glacial sediment.",
      "Composed of a wide variety of particle sizes.",
      "Often forms moraines."
    ]
  },
  {
    "word_no.": 106,
    "word": "HORNFELS",
    "hints": [
      "A fine-grained, hard, compact metamorphic rock.",
      "Formed by contact metamorphism.",
      "Typically dark-colored."
    ]
  },
  {
    "word_no.": 107,
    "word": "HYDROSPHERE",
    "hints": [
      "All the waters on the Earth's surface, such as lakes and seas.",
      "The realm of water on Earth.",
      "Interacts with the lithosphere and atmosphere."
    ]
  },
  {
    "word_no.": 108,
    "word": "KARST",
    "hints": [
      "A landscape formed from the dissolution of soluble rocks.",
      "Characterized by sinkholes, caves, and underground streams.",
      "Common in areas with limestone and gypsum."
    ]
  },
  {
    "word_no.": 109,
    "word": "KIMBERLITE",
    "hints": [
      "A type of igneous rock sometimes containing diamonds.",
      "Found in volcanic pipes.",
      "A significant source of diamonds."
    ]
  },
  {
    "word_no.": 110,
    "word": "LITHIFICATION",
    "hints": [
      "The process in which sediments compact under pressure.",
      "Forms a solid rock.",
      "A key part of the rock cycle."
    ]
  },
  {
    "word_no.": 111,
    "word": "MAGNETITE",
    "hints": [
      "A mineral and one of the main iron ores.",
      "Has a strong magnetic attraction.",
      "Black or brownish-black with a metallic luster."
    ]
  },
  {
    "word_no.": 112,
    "word": "MOHS SCALE",
    "hints": [
      "A qualitative ordinal scale of mineral hardness.",
      "Ranges from 1 (talc) to 10 (diamond).",
      "Used to identify minerals."
    ]
  },
  {
    "word_no.": 113,
    "word": "OASIS",
    "hints": [
      "A fertile spot in a desert.",
      "Where water is found.",
      "Often formed around a spring."
    ]
  },
  {
    "word_no.": 114,
    "word": "PANGEA",
    "hints": [
      "The supercontinent that existed during the late Paleozoic and early Mesozoic eras.",
      "Broke apart due to plate tectonics.",
      "The name means 'all earth' in Greek."
    ]
  },
  {
    "word_no.": 115,
    "word": "PETRIFIED WOOD",
    "hints": [
      "A type of fossil.",
      "The organic material has been replaced by minerals.",
      "Retains the original structure of the wood."
    ]
  },
  {
    "word_no.": 116,
    "word": "QUARTZITE",
    "hints": [
      "A hard, non-foliated metamorphic rock.",
      "Formed from pure quartz sandstone.",
      "Resistant to weathering."
    ]
  },
  {
    "word_no.": 117,
    "word": "RADIOCARBON DATING",
    "hints": [
      "A method for determining the age of an object.",
      "Based on the properties of a certain isotope of carbon.",
      "Used to date organic remains up to 50,000 years old."
    ]
  },
  {
    "word_no.": 118,
    "word": "RIFT VALLEY",
    "hints": [
      "A linear-shaped lowland.",
      "Formed by the action of a geologic fault.",
      "The East African one is a notable example."
    ]
  },
  {
    "word_no.": 119,
    "word": "RIPPLE MARKS",
    "hints": [
      "Undulations on the surface of a rock.",
      "Formed in sand or mud by wind, water, or waves.",
      "Evidence of past environments."
    ]
  },
  {
    "word_no.": 120,
    "word": "SALT DOME",
    "hints": [
      "A dome-shaped structure in sedimentary rocks.",
      "Formed by the upward movement of a mass of salt.",
      "Often associated with oil and gas deposits."
    ]
  },
  {
    "word_no.": 121,
    "word": "SEISMOGRAPH",
    "hints": [
      "An instrument used to detect and record seismic waves.",
      "Used to study earthquakes.",
      "Measures ground motion."
    ]
  },
  {
    "word_no.": 122,
    "word": "STRATA",
    "hints": [
      "Layers of sedimentary rock or soil.",
      "Studied in stratigraphy.",
      "Often seen in canyon walls."
    ]
  },
  {
    "word_no.": 123,
    "word": "SUBMARINE CANYON",
    "hints": [
      "A steep-sided valley cut into the sea floor.",
      "Often found on the continental slope.",
      "Can be larger than terrestrial canyons."
    ]
  },
  {
    "word_no.": 124,
    "word": "THERMAL VENTS",
    "hints": [
      "Fissures on the seafloor from which geothermally heated water issues.",
      "Supports unique ecosystems.",
      "Also known as hydrothermal vents."
    ]
  },
  {
    "word_no.": 125,
    "word": "TILLITE",
    "hints": [
      "A type of sedimentary rock formed from glacial till.",
      "Consists of consolidated rock fragments.",
      "Evidence of ancient ice ages."
    ]
  },
  {
    "word_no.": 126,
    "word": "TOPOGRAPHY",
    "hints": [
      "The study of the forms and features of land surfaces.",
      "The arrangement of the natural and artificial physical features of an area.",
      "Includes hills, valleys, and rivers."
    ]
  },
  {
    "word_no.": 127,
    "word": "TUFF",
    "hints": [
      "A type of rock made of volcanic ash.",
      "Formed from the ejection of volcanic material.",
      "A type of igneous rock."
    ]
  },
  {
    "word_no.": 128,
    "word": "VOLCANIC ARC",
    "hints": [
      "A chain of volcanoes.",
      "Forms above a subducting plate.",
      "Examples include the Andes and the Aleutian Islands."
    ]
  },
  {
    "word_no.": 129,
    "word": "VOLCANIC BOMB",
    "hints": [
      "A mass of molten rock ejected during a volcanic eruption.",
      "Cool and solidify before they reach the ground.",
      "Larger than lapilli."
    ]
  },
  {
    "word_no.": 130,
    "word": "XENOLITH",
    "hints": [
      "A piece of rock found within another rock.",
      "Often found in igneous rock, but not derived from the original magma.",
      "Means 'foreign rock' in Greek."
    ]
  },
  {
    "word_no.": 131,
    "word": "ABRASION",
    "hints": [
      "A process of erosion.",
      "Caused by the wearing away of rock by transported particles.",
      "Can be caused by wind, water, or ice."
    ]
  },
  {
    "word_no.": 132,
    "word": "ACCRETIONARY WEDGE",
    "hints": [
      "A mass of sediment that is scraped off a subducting plate.",
      "Forms a prism-shaped body of rock.",
      "Located at a subduction zone."
    ]
  },
  {
    "word_no.": 133,
    "word": "ALLUVIAL FAN",
    "hints": [
      "A fan-shaped deposit of sediment.",
      "Forms at the base of a mountain range.",
      "Created by a stream that exits a narrow valley."
    ]
  },
  {
    "word_no.": 134,
    "word": "AMETHYST",
    "hints": [
      "A purple variety of quartz.",
      "A popular gemstone.",
      "The birthstone for February."
    ]
  },
  {
    "word_no.": 135,
    "word": "AQUIFER",
    "hints": [
      "An underground layer of water-bearing permeable rock.",
      "Can be a source of groundwater.",
      "Often tapped by wells."
    ]
  },
  {
    "word_no.": 136,
    "word": "ARETE",
    "hints": [
      "A thin, knife-like ridge of rock.",
      "Formed by two glaciers eroding opposite sides of a mountain.",
      "A common feature in glaciated landscapes."
    ]
  },
  {
    "word_no.": 137,
    "word": "BASIN",
    "hints": [
      "A low-lying area of land.",
      "Often surrounded by higher ground.",
      "Can be a site of sediment deposition."
    ]
  },
  {
    "word_no.": 138,
    "word": "BEACH",
    "hints": [
      "A landform alongside a body of water.",
      "Consists of loose particles such as sand, pebbles, or shells.",
      "Where the land meets the sea."
    ]
  },
  {
    "word_no.": 139,
    "word": "BIOTITE",
    "hints": [
      "A common rock-forming mineral of the mica family.",
      "Dark-colored and shiny.",
      "Found in igneous and metamorphic rocks."
    ]
  },
  {
    "word_no.": 140,
    "word": "BRECCIA",
    "hints": [
      "A clastic sedimentary rock composed of large, angular fragments.",
      "Unlike conglomerate, its fragments are sharp.",
      "Forms from the cementation of rubble."
    ]
  },
  {
    "word_no.": 141,
    "word": "CHALCEDONY",
    "hints": [
      "A cryptocrystalline form of silica.",
      "Includes varieties like agate and onyx.",
      "Has a waxy luster."
    ]
  },
  {
    "word_no.": 142,
    "word": "CHALK",
    "hints": [
      "A soft, porous form of limestone.",
      "Composed of the shells of tiny marine organisms.",
      "Used as a writing tool."
    ]
  },
  {
    "word_no.": 143,
    "word": "CINDER CONE",
    "hints": [
      "A steep conical hill of loose pyroclastic fragments.",
      "Forms around a volcanic vent.",
      "One of the simplest types of volcanoes."
    ]
  },
  {
    "word_no.": 144,
    "word": "CLEAVAGE",
    "hints": [
      "The tendency of a mineral to break along flat planar surfaces.",
      "A useful characteristic for mineral identification.",
      "Perfect or poor, depending on the mineral."
    ]
  },
  {
    "word_no.": 145,
    "word": "COLUMNAR JOINTING",
    "hints": [
      "A geological structure where parallel columns form in a rock body.",
      "Common in basalt flows and other volcanic rocks.",
      "Devils Tower in Wyoming is a famous example."
    ]
  },
  {
    "word_no.": 146,
    "word": "COMPRESSION",
    "hints": [
      "A type of stress that squeezes a rock mass.",
      "Causes shortening and thickening of the crust.",
      "Associated with convergent plate boundaries."
    ]
  },
  {
    "word_no.": 147,
    "word": "CONTACT METAMORPHISM",
    "hints": [
      "Metamorphism caused by heat from a magma intrusion.",
      "Occurs near the border of a magma body.",
      "Forms a halo of metamorphic rock."
    ]
  },
  {
    "word_no.": 148,
    "word": "CONTINENTAL SHELF",
    "hints": [
      "The extended perimeter of a continent.",
      "Covered by relatively shallow seas.",
      "Rich in marine life and resources."
    ]
  },
  {
    "word_no.": 149,
    "word": "CRYSTAL",
    "hints": [
      "A solid material whose constituents are arranged in a highly ordered microscopic structure.",
      "A key feature of many minerals.",
      "Has a repeating pattern."
    ]
  },
  {
    "word_no.": 150,
    "word": "DIATREMES",
    "hints": [
      "A volcanic pipe of brecciated rock.",
      "Formed by a violent, gas-charged volcanic eruption.",
      "Can be a source of diamonds."
    ]
  },
  {
    "word_no.": 151,
    "word": "DRUMLIN",
    "hints": [
      "An elongated hill of glacial drift.",
      "Shaped like an inverted spoon.",
      "Points in the direction of glacial flow."
    ]
  },
  {
    "word_no.": 152,
    "word": "EOLIAN",
    "hints": [
      "Relating to or caused by wind.",
      "Describes deposits like sand dunes and loess.",
      "A type of geological process."
    ]
  },
  {
    "word_no.": 153,
    "word": "EPIROGENY",
    "hints": [
      "Broad, gentle warping of the Earth's crust.",
      "Causes uplift or subsidence.",
      "Can lead to the formation of large domes or basins."
    ]
  },
  {
    "word_no.": 154,
    "word": "FISSURE",
    "hints": [
      "A long, narrow crack or opening.",
      "Can be a vent for a volcano.",
      "A type of geological fracture."
    ]
  },
  {
    "word_no.": 155,
    "word": "FLUVIAL",
    "hints": [
      "Relating to a river.",
      "Describes processes or landforms created by streams.",
      "Opposite of glacial."
    ]
  },
  {
    "word_no.": 156,
    "word": "GEODE",
    "hints": [
      "A hollow rock with an internal cavity lined with crystals.",
      "Often spherical in shape.",
      "Can be cracked open to reveal its beauty."
    ]
  },
  {
    "word_no.": 157,
    "word": "GEOSYNCLINE",
    "hints": [
      "An older geological theory.",
      "A large-scale depression in the Earth's crust.",
      "Supposedly filled with thick sediments to form mountain belts."
    ]
  },
  {
    "word_no.": 158,
    "word": "GLAUCONITE",
    "hints": [
      "A green mineral of the mica group.",
      "An indicator of marine sedimentary environments.",
      "Often found in greensand formations."
    ]
  },
  {
    "word_no.": 159,
    "word": "GRANODIORITE",
    "hints": [
      "A coarse-grained intrusive igneous rock.",
      "Similar to granite, but with more plagioclase feldspar.",
      "A major component of many batholiths."
    ]
  },
  {
    "word_no.": 160,
    "word": "GYPSUM",
    "hints": [
      "A soft sulfate mineral.",
      "Used to make plaster and drywall.",
      "A common evaporite mineral."
    ]
  },
  {
    "word_no.": 161,
    "word": "HORNBLENDE",
    "hints": [
      "A complex inosilicate mineral.",
      "A common dark-colored mineral.",
      "Found in igneous and metamorphic rocks."
    ]
  },
  {
    "word_no.": 162,
    "word": "ICE AGE",
    "hints": [
      "A period of long-term reduction in the temperature of the Earth's climate.",
      "Results in the expansion of continental ice sheets.",
      "The last one ended about 11,700 years ago."
    ]
  },
  {
    "word_no.": 163,
    "word": "INTRUSION",
    "hints": [
      "The process of magma moving into a pre-existing rock formation.",
      "Also refers to the resulting rock body.",
      "A term for igneous rock that cooled underground."
    ]
  },
  {
    "word_no.": 164,
    "word": "ISOSTASY",
    "hints": [
      "The state of gravitational equilibrium between the Earth's lithosphere and asthenosphere.",
      "Explains why mountains have deep 'roots'.",
      "Relates to the buoyancy of the crust."
    ]
  },
  {
    "word_no.": 165,
    "word": "KETTLE",
    "hints": [
      "A shallow, sediment-filled body of water.",
      "Formed by the melting of a buried block of glacial ice.",
      "A common feature in moraines."
    ]
  },
  {
    "word_no.": 166,
    "word": "LACCOLITH",
    "hints": [
      "A dome-shaped body of intrusive igneous rock.",
      "Forms from magma that pushes up the overlying layers.",
      "The Henry Mountains of Utah are an example."
    ]
  },
  {
    "word_no.": 167,
    "word": "LAPIS LAZULI",
    "hints": [
      "A deep-blue metamorphic rock.",
      "Composed primarily of lazurite.",
      "Prized since antiquity for its intense color."
    ]
  },
  {
    "word_no.": 168,
    "word": "LITHOSPERIC PLATE",
    "hints": [
      "One of the several huge, rigid slabs of the Earth's crust.",
      "In constant motion, driven by convection in the mantle.",
      "The main components of plate tectonics."
    ]
  },
  {
    "word_no.": 169,
    "word": "MAGMATIC DIKE",
    "hints": [
      "A sheet of magma that cuts through existing rock layers.",
      "Can be a few inches to many feet wide.",
      "A type of intrusive igneous rock formation."
    ]
  },
  {
    "word_no.": 170,
    "word": "MANTLE PLUME",
    "hints": [
      "An upwelling of abnormally hot rock within the Earth's mantle.",
      "Thought to be the cause of hotspots.",
      "A proposed cause of some volcanism."
    ]
  },
  {
    "word_no.": 171,
    "word": "MASS WASTING",
    "hints": [
      "The geomorphic process by which soil, sand, and rock move downslope.",
      "Can be a slow creep or a sudden landslide.",
      "A form of erosion."
    ]
  },
  {
    "word_no.": 172,
    "word": "METAMORPHISM",
    "hints": [
      "The process of changing the structure and composition of a rock.",
      "Caused by heat, pressure, or chemical alteration.",
      "Creates metamorphic rocks."
    ]
  },
  {
    "word_no.": 173,
    "word": "MOHO",
    "hints": [
      "The boundary between the Earth's crust and the mantle.",
      "Short for Mohorovicic discontinuity.",
      "Marks a change in seismic wave velocity."
    ]
  },
  {
    "word_no.": 174,
    "word": "MONOCLINE",
    "hints": [
      "A bend in rock strata.",
      "Layers are horizontal on either side of a single fold.",
      "A simple type of fold."
    ]
  },
  {
    "word_no.": 175,
    "word": "OAK",
    "hints": [
      "A common type of tree.",
      "Not a mineral, but often a source of petrified wood.",
      "A tree known for its strength."
    ]
  },
  {
    "word_no.": 176,
    "word": "OBLIQUE SLIP",
    "hints": [
      "A type of fault movement.",
      "Combines strike-slip and dip-slip motion.",
      "Movement is both horizontal and vertical."
    ]
  },
  {
    "word_no.": 177,
    "word": "OPIOLITE",
    "hints": [
      "A section of oceanic crust and upper mantle.",
      "Thought to be a piece of oceanic lithosphere obducted onto continental crust.",
      "Provides evidence for plate tectonics."
    ]
  },
  {
    "word_no.": 178,
    "word": "ORDOVICIAN",
    "hints": [
      "A geologic period and system of the Paleozoic Era.",
      "Follows the Cambrian Period.",
      "Known for the diversification of marine life."
    ]
  },
  {
    "word_no.": 179,
    "word": "OUTWASH PLAIN",
    "hints": [
      "A plain formed by glacial sediments deposited by meltwater.",
      "Can be found in front of a glacier.",
      "Also known as a sandur."
    ]
  },
  {
    "word_no.": 180,
    "word": "PALEOGEOGRAPHY",
    "hints": [
      "The study of geographical features at particular times in the geological past.",
      "Looks at the reconstruction of ancient continents.",
      "A sub-discipline of geology."
    ]
  },
  {
    "word_no.": 181,
    "word": "PALEOMAGNETISM",
    "hints": [
      "The study of the record of the Earth's magnetic field in rocks.",
      "Provides evidence for plate tectonics.",
      "Shows how continents have drifted over time."
    ]
  },
  {
    "word_no.": 182,
    "word": "PERIDOTITE",
    "hints": [
      "A dense, coarse-grained igneous rock.",
      "The dominant rock type in the Earth's upper mantle.",
      "The source of basaltic magma."
    ]
  },
  {
    "word_no.": 183,
    "word": "PERMIAN",
    "hints": [
      "The last period of the Paleozoic Era.",
      "Ended with the largest mass extinction in Earth's history.",
      "Followed by the Triassic Period."
    ]
  },
  {
    "word_no.": 184,
    "word": "PHANEROZOIC",
    "hints": [
      "The current geologic eon.",
      "Means 'visible life' in Greek.",
      "Includes the Paleozoic, Mesozoic, and Cenozoic eras."
    ]
  },
  {
    "word_no.": 185,
    "word": "PIEDMONT",
    "hints": [
      "A gentle slope leading from the base of mountains to a plain.",
      "The area at the foot of a mountain.",
      "The term for the southeastern US region."
    ]
  },
  {
    "word_no.": 186,
    "word": "PLAGIOCLASE",
    "hints": [
      "A series of tectosilicate minerals within the feldspar group.",
      "A major component of the Earth's crust.",
      "Ranges in composition from albite to anorthite."
    ]
  },
  {
    "word_no.": 187,
    "word": "PLUTONIC",
    "hints": [
      "A type of igneous rock.",
      "Formed from magma that cooled slowly underground.",
      "Also known as intrusive igneous rock."
    ]
  },
  {
    "word_no.": 188,
    "word": "POROSITY",
    "hints": [
      "A measure of the void spaces in a material.",
      "A factor in how much water a rock can hold.",
      "The ratio of the volume of voids to the total volume."
    ]
  },
  {
    "word_no.": 189,
    "word": "PYROCLASTIC FLOW",
    "hints": [
      "A fast-moving current of hot gas and volcanic matter.",
      "Extremely dangerous to life.",
      "Associated with explosive volcanic eruptions."
    ]
  },
  {
    "word_no.": 190,
    "word": "REGOLITH",
    "hints": [
      "A layer of loose, heterogeneous superficial material.",
      "Covers solid rock.",
      "Found on Earth, the Moon, Mars, and other planetary bodies."
    ]
  },
  {
    "word_no.": 191,
    "word": "ROSE QUARTZ",
    "hints": [
      "A variety of quartz.",
      "Has a pale pink to rose red hue.",
      "Often used in jewelry and carvings."
    ]
  },
  {
    "word_no.": 192,
    "word": "SALTATION",
    "hints": [
      "The process of a particle moving along in a series of short hops.",
      "Caused by wind or water.",
      "A method of sediment transport."
    ]
  },
  {
    "word_no.": 193,
    "word": "SAND DUNE",
    "hints": [
      "A hill of sand built by wind.",
      "Common in deserts and coastal areas.",
      "Can be of various shapes and sizes."
    ]
  },
  {
    "word_no.": 194,
    "word": "SILICATE",
    "hints": [
      "A compound containing a silicon-oxygen tetrahedron.",
      "The most common mineral group in the Earth's crust.",
      "Quartz, feldspar, and mica are examples."
    ]
  },
  {
    "word_no.": 195,
    "word": "SLUMP",
    "hints": [
      "A form of mass wasting that occurs when a coherent mass of rock or soil moves down a slope.",
      "Often leaves a curved scar at the top.",
      "A type of landslide."
    ]
  },
  {
    "word_no.": 196,
    "word": "STRATIFIED",
    "hints": [
      "Arranged in layers or strata.",
      "A characteristic of many sedimentary rocks.",
      "Means 'layered'."
    ]
  },
  {
    "word_no.": 197,
    "word": "STRIKE-SLIP",
    "hints": [
      "A type of fault movement.",
      "Motion is primarily horizontal.",
      "The San Andreas Fault is an example."
    ]
  },
  {
    "word_no.": 198,
    "word": "SUBLIMATION",
    "hints": [
      "The transition of a substance directly from the solid to the gas state.",
      "Can happen with glacial ice.",
      "A physical process."
    ]
  },
  {
    "word_no.": 199,
    "word": "TABULAR",
    "hints": [
      "Describing a rock body that is flat and plate-like.",
      "Can refer to dikes and sills.",
      "A geological shape."
    ]
  },
  {
    "word_no.": 200,
    "word": "TERRACE",
    "hints": [
      "A level, raised piece of ground.",
      "Can be a river terrace or a marine terrace.",
      "Formed by erosion and deposition."
    ]
  },
  {
    "word_no.": 201,
    "word": "THOLEIITE",
    "hints": [
      "A type of basalt.",
      "The most common magma type erupted on Earth.",
      "Found at mid-ocean ridges."
    ]
  },
  {
    "word_no.": 202,
    "word": "THRUST FAULT",
    "hints": [
      "A type of reverse fault with a low angle of dip.",
      "The hanging wall moves up and over the footwall.",
      "Associated with mountain building."
    ]
  },
  {
    "word_no.": 203,
    "word": "TOURMALINE",
    "hints": [
      "A crystalline borosilicate mineral.",
      "Used as a gemstone.",
      "Comes in a wide variety of colors."
    ]
  },
  {
    "word_no.": 204,
    "word": "TRAVERTINE",
    "hints": [
      "A form of limestone deposited by mineral springs.",
      "Often used in flooring and cladding.",
      "Can have a banded appearance."
    ]
  },
  {
    "word_no.": 205,
    "word": "TURBIDITE",
    "hints": [
      "A sedimentary deposit of a turbidity current.",
      "Characterized by graded bedding.",
      "Found in deep marine environments."
    ]
  },
  {
    "word_no.": 206,
    "word": "VARVES",
    "hints": [
      "Annual layers of sediment or sedimentary rock.",
      "Often found in glacial lakes.",
      "Each pair of layers represents a single year's deposition."
    ]
  },
  {
    "word_no.": 207,
    "word": "XENOTIME",
    "hints": [
      "A yttrium phosphate mineral.",
      "A minor source of rare-earth elements.",
      "Often found in pegmatites."
    ]
  },
  {
    "word_no.": 208,
    "word": "YAMAT",
    "hints": [
      "A type of meteorite.",
      "Discovered in Antarctica.",
      "A Japanese name for the Queen Maud Land area."
    ]
  },
  {
    "word_no.": 209,
    "word": "ZEOLITE",
    "hints": [
      "A family of aluminosilicate minerals.",
      "Used as a catalyst and in water purification.",
      "Has a porous structure."
    ]
  },
  {
    "word_no.": 210,
    "word": "BATHOLITH",
    "hints": [
      "A large body of intrusive igneous rock.",
      "Covers an area of at least 100 square kilometers.",
      "The Sierra Nevada Mountains are an example of this."
    ]
  },
  {
    "word_no.": 211,
    "word": "CIRQUE",
    "hints": [
      "A bowl-shaped hollow at the head of a glacial valley.",
      "Formed by glacial erosion.",
      "Often has a steep headwall."
    ]
  },
  {
    "word_no.": 212,
    "word": "DIATOMITE",
    "hints": [
      "A soft, siliceous sedimentary rock.",
      "Composed of the fossilized remains of diatoms.",
      "Used as a filter and abrasive."
    ]
  },
  {
    "word_no.": 213,
    "word": "GEOCENTRIC",
    "hints": [
      "A historical model of the solar system.",
      "Places the Earth at the center.",
      "Disproven by the heliocentric model."
    ]
  },
  {
    "word_no.": 214,
    "word": "GRAVEL",
    "hints": [
      "A loose aggregation of rock fragments.",
      "Larger than sand, but smaller than boulders.",
      "Used in construction and landscaping."
    ]
  },
  {
    "word_no.": 215,
    "word": "HOGBACK",
    "hints": [
      "A long, narrow ridge.",
      "Formed by steeply dipping rock layers.",
      "The steeply dipping version of a cuesta."
    ]
  },
  {
    "word_no.": 216,
    "word": "JASPER",
    "hints": [
      "An opaque, impure variety of silica.",
      "Often red, yellow, brown, or green.",
      "A popular gemstone."
    ]
  },
  {
    "word_no.": 217,
    "word": "JOINT",
    "hints": [
      "A fracture in a rock where no movement has taken place.",
      "Can be formed by stress.",
      "A common feature in many rock exposures."
    ]
  },
  {
    "word_no.": 218,
    "word": "KAME",
    "hints": [
      "An irregularly shaped hill or mound.",
      "Composed of stratified sand and gravel.",
      "Deposited by meltwater in a glacier."
    ]
  },
  {
    "word_no.": 219,
    "word": "KEGEL",
    "hints": [
      "A small, steep-sided volcanic cone.",
      "Forms from explosive eruptions.",
      "A type of volcanic landform."
    ]
  },
  {
    "word_no.": 220,
    "word": "KIMBERLITE",
    "hints": [
      "A type of potassic volcanic rock.",
      "The most important source of diamonds.",
      "Found in volcanic pipes."
    ]
  },
  {
    "word_no.": 221,
    "word": "KNOB",
    "hints": [
      "A small, isolated hill.",
      "Can be a volcanic neck.",
      "A type of landform."
    ]
  },
  {
    "word_no.": 222,
    "word": "LAVA FLOW",
    "hints": [
      "A flowing stream of molten rock.",
      "Can be pahoehoe or a'a.",
      "Creates new land."
    ]
  },
  {
    "word_no.": 223,
    "word": "LOESS",
    "hints": [
      "A fine, wind-blown sediment.",
      "Often forms fertile soil.",
      "Found in large deposits in China and the American Midwest."
    ]
  },
  {
    "word_no.": 224,
    "word": "MAGNETOMETER",
    "hints": [
      "An instrument that measures magnetic fields.",
      "Used in geophysics to study the Earth's magnetic field.",
      "Helped to prove seafloor spreading."
    ]
  },
  {
    "word_no.": 225,
    "word": "MANGANESE NODULE",
    "hints": [
      "A rock concretion found on the seabed.",
      "Rich in manganese and iron oxides.",
      "A potential source of metals."
    ]
  },
  {
    "word_no.": 226,
    "word": "MEANDER",
    "hints": [
      "A winding curve or bend in a river.",
      "Forms as a river erodes its outer banks.",
      "Creates oxbow lakes."
    ]
  },
  {
    "word_no.": 227,
    "word": "MOHOR",
    "hints": [
      "A popular term for the Mohorovicic discontinuity.",
      "The boundary between the crust and mantle.",
      "Also known as the Moho."
    ]
  },
  {
    "word_no.": 228,
    "word": "OBSIDIAN",
    "hints": [
      "A naturally occurring volcanic glass.",
      "Forms from the rapid cooling of lava.",
      "Used by ancient cultures for cutting tools."
    ]
  },
  {
    "word_no.": 229,
    "word": "PALLASITE",
    "hints": [
      "A type of stony-iron meteorite.",
      "Composed of olivine crystals in an iron-nickel matrix.",
      "A beautiful and rare type of meteorite."
    ]
  },
  {
    "word_no.": 230,
    "word": "PEBBLE",
    "hints": [
      "A clast of rock.",
      "A small, rounded stone.",
      "Found on beaches and riverbeds."
    ]
  },
  {
    "word_no.": 231,
    "word": "PEDIMENT",
    "hints": [
      "A broad, gently sloping erosional surface.",
      "Found at the base of a steeper mountain front.",
      "Common in arid and semi-arid regions."
    ]
  },
  {
    "word_no.": 232,
    "word": "PEGMATITE",
    "hints": [
      "An igneous rock with very large crystals.",
      "Often a source of rare minerals and gemstones.",
      "Forms from the final stages of magma crystallization."
    ]
  },
  {
    "word_no.": 233,
    "word": "PHOSPHORITE",
    "hints": [
      "A non-clastic sedimentary rock.",
      "Contains a high concentration of phosphate minerals.",
      "A source of phosphorus for fertilizer."
    ]
  },
  {
    "word_no.": 234,
    "word": "PILLOW LAVA",
    "hints": [
      "Lava that has been extruded underwater.",
      "Forms pillow-shaped masses.",
      "Evidence of submarine volcanic eruptions."
    ]
  },
  {
    "word_no.": 235,
    "word": "PRECAMBRIAN",
    "hints": [
      "The period of time before the Cambrian Period.",
      "Represents about 88% of geologic time.",
      "Divided into the Hadean, Archean, and Proterozoic eons."
    ]
  },
  {
    "word_no.": 236,
    "word": "PYROCLASTIC",
    "hints": [
      "Relating to or consisting of fragments of rock ejected from a volcano.",
      "Means 'fire-broken' in Greek.",
      "Describes volcanic ash, bombs, and cinders."
    ]
  },
  {
    "word_no.": 237,
    "word": "QUATERNARY",
    "hints": [
      "The current and most recent geologic period.",
      "Began 2.58 million years ago.",
      "Includes the Holocene and Pleistocene epochs."
    ]
  },
  {
    "word_no.": 238,
    "word": "REVERSE FAULT",
    "hints": [
      "A type of fault where the hanging wall moves up relative to the footwall.",
      "Caused by compressional stress.",
      "The opposite of a normal fault."
    ]
  },
  {
    "word_no.": 239,
    "word": "RHYOLITE",
    "hints": [
      "A fine-grained igneous rock.",
      "The volcanic equivalent of granite.",
      "Often pink or gray."
    ]
  },
  {
    "word_no.": 240,
    "word": "RICHARDSON NUMBER",
    "hints": [
      "A dimensionless number used in fluid dynamics.",
      "Used in oceanography and atmospheric science.",
      "Relates buoyancy to shear."
    ]
  },
  {
    "word_no.": 241,
    "word": "RUST",
    "hints": [
      "A reddish-brown flaky coating on iron or steel.",
      "A product of oxidation.",
      "A form of chemical weathering."
    ]
  },
  {
    "word_no.": 242,
    "word": "SANIDINE",
    "hints": [
      "A tectosilicate mineral of the feldspar group.",
      "Typically found in volcanic rocks.",
      "A high-temperature form of orthoclase."
    ]
  },
  {
    "word_no.": 243,
    "word": "SCORIA",
    "hints": [
      "A highly vesicular, dark-colored volcanic rock.",
      "Forms from basaltic magma.",
      "Often red or brown."
    ]
  },
  {
    "word_no.": 244,
    "word": "SEICHE",
    "hints": [
      "A standing wave oscillating in a body of water.",
      "Can be found in lakes and partially enclosed seas.",
      "Sometimes called a 'sloshing wave'."
    ]
  },
  {
    "word_no.": 245,
    "word": "SHIELD VOLCANO",
    "hints": [
      "A type of volcano with broad, gently sloping sides.",
      "Formed by eruptions of low-viscosity lava.",
      "Mauna Loa in Hawaii is an example."
    ]
  },
  {
    "word_no.": 246,
    "word": "SILL",
    "hints": [
      "A tabular sheet of igneous rock.",
      "Intruded between layers of older rock.",
      "Parallel to the existing rock layers."
    ]
  },
  {
    "word_no.": 247,
    "word": "SPILITE",
    "hints": [
      "A fine-grained, altered basaltic rock.",
      "Forms from submarine volcanism.",
      "Contains albite and chlorite."
    ]
  },
  {
    "word_no.": 248,
    "word": "STRAIGHT FAULT",
    "hints": [
      "A type of fault with a straight fault plane.",
      "A simple type of fault.",
      "The opposite of a curved fault."
    ]
  },
  {
    "word_no.": 249,
    "word": "SUBMARINE FAN",
    "hints": [
      "A fan-shaped deposit of sediment on the deep ocean floor.",
      "Forms at the mouth of an underwater canyon.",
      "Created by turbidity currents."
    ]
  },
  {
    "word_no.": 250,
    "word": "SUBLITHOSPERIC",
    "hints": [
      "Located beneath the lithosphere.",
      "A term for the upper mantle.",
      "Part of the Earth's interior."
    ]
  },
  {
    "word_no.": 251,
    "word": "SUPERCONTINENT",
    "hints": [
      "A large landmass made of more than one continental core.",
      "Pangea is a famous example.",
      "Forms and breaks up in a cycle."
    ]
  },
  {
    "word_no.": 252,
    "word": "SYENITE",
    "hints": [
      "A coarse-grained intrusive igneous rock.",
      "Similar to granite, but with little to no quartz.",
      "Rich in alkali feldspar."
    ]
  },
  {
    "word_no.": 253,
    "word": "TALUS",
    "hints": [
      "A slope formed by an accumulation of rock debris.",
      "Found at the base of a cliff or steep slope.",
      "Also known as a scree slope."
    ]
  },
  {
    "word_no.": 254,
    "word": "TEKTITE",
    "hints": [
      "A small, natural glass body.",
      "Formed from the impact of large meteorites.",
      "Often found in certain strewn fields."
    ]
  },
  {
    "word_no.": 255,
    "word": "TEXTURE",
    "hints": [
      "The size, shape, and arrangement of the mineral grains in a rock.",
      "A key characteristic for rock identification.",
      "Can be fine-grained, coarse-grained, or glassy."
    ]
  },
  {
    "word_no.": 256,
    "word": "TRANSFORM FAULT",
    "hints": [
      "A type of strike-slip fault.",
      "Marks a plate boundary.",
      "Connects other types of plate boundaries."
    ]
  },
  {
    "word_no.": 257,
    "word": "TRILOBITE",
    "hints": [
      "An extinct group of arthropods.",
      "Lived from the Cambrian to the Permian periods.",
      "A very common fossil."
    ]
  },
  {
    "word_no.": 258,
    "word": "TSUNAMI",
    "hints": [
      "A series of ocean waves.",
      "Caused by large-scale disturbances like underwater earthquakes or volcanic eruptions.",
      "A destructive natural disaster."
    ]
  },
  {
    "word_no.": 259,
    "word": "ULTRAMAFIC",
    "hints": [
      "A class of igneous rocks.",
      "Contains very low silica content.",
      "Peridotite is an example."
    ]
  },
  {
    "word_no.": 260,
    "word": "UNCONFORMITY",
    "hints": [
      "A break in the geologic record.",
      "Represents a period of erosion or non-deposition.",
      "A surface between two rock strata."
    ]
  },
  {
    "word_no.": 261,
    "word": "V-SHAPED VALLEY",
    "hints": [
      "A valley formed by a river.",
      "Has a distinctive cross-section.",
      "The opposite of a U-shaped valley."
    ]
  },
  {
    "word_no.": 262,
    "word": "WATER TABLE",
    "hints": [
      "The upper level of the saturated zone of groundwater.",
      "Can fluctuate with rainfall.",
      "The level below which the ground is saturated with water."
    ]
  },
  {
    "word_no.": 263,
    "word": "ACID RAIN",
    "hints": [
      "Rainfall made sufficiently acidic by atmospheric pollution.",
      "A form of chemical weathering.",
      "Harmful to forests and lakes."
    ]
  },
  {
    "word_no.": 264,
    "word": "ALGAE",
    "hints": [
      "A diverse group of aquatic organisms.",
      "Can form deposits that become sedimentary rocks.",
      "Often found in ponds and lakes."
    ]
  },
  {
    "word_no.": 265,
    "word": "ALLANITE",
    "hints": [
      "A silicate mineral.",
      "A complex mineral containing rare-earth elements.",
      "Can be a source of cerium."
    ]
  },
  {
    "word_no.": 266,
    "word": "AMPHIBOLITE",
    "hints": [
      "A coarse-grained metamorphic rock.",
      "Composed mainly of amphibole and plagioclase.",
      "Forms from the metamorphism of basalt."
    ]
  },
  {
    "word_no.": 267,
    "word": "AQUATARD",
    "hints": [
      "A low-permeability layer of rock or sediment.",
      "Slows the movement of groundwater.",
      "A barrier to groundwater flow."
    ]
  },
  {
    "word_no.": 268,
    "word": "ARAGONITE",
    "hints": [
      "A carbonate mineral.",
      "A polymorph of calcium carbonate.",
      "Found in mollusk shells and caves."
    ]
  },
  {
    "word_no.": 269,
    "word": "AUGEN GNEISS",
    "hints": [
      "A metamorphic rock with large, eye-shaped crystals.",
      "Forms from the metamorphism of granite.",
      "The 'augen' are feldspar crystals."
    ]
  },
  {
    "word_no.": 270,
    "word": "BARYTE",
    "hints": [
      "A mineral consisting of barium sulfate.",
      "Used in drilling mud.",
      "Heavy and non-toxic."
    ]
  },
  {
    "word_no.": 271,
    "word": "BOUDINAGE",
    "hints": [
      "A structure in geology.",
      "Forms when a competent layer is stretched.",
      "Looks like a string of sausages."
    ]
  },
  {
    "word_no.": 272,
    "word": "BRYOZOANS",
    "hints": [
      "Aquatic invertebrate animals.",
      "Can form colonies.",
      "Often found as fossils in sedimentary rock."
    ]
  },
  {
    "word_no.": 273,
    "word": "CALDERA",
    "hints": [
      "A large, circular depression.",
      "Formed by the collapse of a volcano.",
      "Crater Lake in Oregon is an example."
    ]
  },
  {
    "word_no.": 274,
    "word": "CHALCOPYRITE",
    "hints": [
      "A copper iron sulfide mineral.",
      "A major source of copper ore.",
      "Has a brassy-yellow color."
    ]
  },
  {
    "word_no.": 275,
    "word": "CHERT",
    "hints": [
      "A hard, fine-grained sedimentary rock.",
      "Composed of microcrystalline quartz.",
      "Forms in marine environments."
    ]
  },
  {
    "word_no.": 276,
    "word": "CHLORITE",
    "hints": [
      "A group of phyllosilicate minerals.",
      "Green in color.",
      "A common mineral in metamorphic rocks."
    ]
  },
  {
    "word_no.": 277,
    "word": "CHRYSOTILE",
    "hints": [
      "A fibrous variety of serpentine.",
      "A type of asbestos.",
      "Used as a fire-resistant material."
    ]
  },
  {
    "word_no.": 278,
    "word": "CINERITE",
    "hints": [
      "A sedimentary rock.",
      "Composed of volcanic ash and rock fragments.",
      "A type of tuff."
    ]
  },
  {
    "word_no.": 279,
    "word": "COQUINA",
    "hints": [
      "A sedimentary rock.",
      "Composed of fragments of shells and corals.",
      "Forms in shallow marine environments."
    ]
  },
  {
    "word_no.": 280,
    "word": "DIATOMACEOUS EARTH",
    "hints": [
      "A soft, siliceous sedimentary rock.",
      "Composed of the fossilized remains of diatoms.",
      "Used as a filter and abrasive."
    ]
  },
  {
    "word_no.": 281,
    "word": "DRUMLIN",
    "hints": [
      "An elongated hill of glacial drift.",
      "Forms from the movement of a glacier.",
      "Looks like an inverted spoon."
    ]
  },
  {
    "word_no.": 282,
    "word": "EPIDOTE",
    "hints": [
      "A silicate mineral.",
      "Often has a pistachio-green color.",
      "A common mineral in metamorphic rocks."
    ]
  },
  {
    "word_no.": 283,
    "word": "EUSTASY",
    "hints": [
      "A global change in sea level.",
      "Caused by changes in the volume of water in the ocean.",
      "Associated with ice ages."
    ]
  },
  {
    "word_no.": 284,
    "word": "EVAPORITE",
    "hints": [
      "A sedimentary rock.",
      "Formed from the evaporation of water.",
      "Halite and gypsum are examples."
    ]
  },
  {
    "word_no.": 285,
    "word": "FAULT GOUGE",
    "hints": [
      "A fine-grained, clay-rich material.",
      "Forms from the grinding of rocks along a fault.",
      "Found in fault zones."
    ]
  },
  {
    "word_no.": 286,
    "word": "FENNELITE",
    "hints": [
      "A type of volcanic rock.",
      "Contains abundant alkali feldspar.",
      "A rare type of igneous rock."
    ]
  },
  {
    "word_no.": 287,
    "word": "FLUORITE",
    "hints": [
      "A mineral with a cubic crystal system.",
      "Has a wide range of colors.",
      "Has perfect octahedral cleavage."
    ]
  },
  {
    "word_no.": 288,
    "word": "FUMAROLE",
    "hints": [
      "An opening in a planet's crust.",
      "Emits steam and gases from a volcano.",
      "A type of volcanic vent."
    ]
  },
  {
    "word_no.": 289,
    "word": "GALENA",
    "hints": [
      "A lead sulfide mineral.",
      "The main ore of lead.",
      "Has a bright metallic luster."
    ]
  },
  {
    "word_no.": 290,
    "word": "GABBRO",
    "hints": [
      "A coarse-grained intrusive igneous rock.",
      "Compositionally equivalent to basalt.",
      "A key component of the lower oceanic crust."
    ]
  },
  {
    "word_no.": 291,
    "word": "GNEISS",
    "hints": [
      "A foliated metamorphic rock.",
      "Characterized by alternating bands of light and dark minerals.",
      "Forms from the metamorphism of granite."
    ]
  },
  {
    "word_no.": 292,
    "word": "GREENSCHIST",
    "hints": [
      "A metamorphic rock.",
      "Forms under relatively low temperatures and pressures.",
      "Characterized by its green color."
    ]
  },
  {
    "word_no.": 293,
    "word": "HORNFELS",
    "hints": [
      "A fine-grained, hard, compact metamorphic rock.",
      "Forms from contact metamorphism.",
      "Typically dark-colored."
    ]
  },
  {
    "word_no.": 294,
    "word": "ILMENITE",
    "hints": [
      "A titanium-iron oxide mineral.",
      "The primary ore of titanium.",
      "Black with a sub-metallic luster."
    ]
  },
  {
    "word_no.": 295,
    "word": "KYANITE",
    "hints": [
      "A blue aluminosilicate mineral.",
      "Forms at high pressure.",
      "Has variable hardness depending on the direction."
    ]
  },
  {
    "word_no.": 296,
    "word": "LATERITE",
    "hints": [
      "A soil and rock type rich in iron and aluminum.",
      "Forms in hot, wet tropical areas.",
      "Can be a source of bauxite ore."
    ]
  },
  {
    "word_no.": 297,
    "word": "LODE",
    "hints": [
      "A deposit of metallic ore.",
      "Often found in a vein or fissure.",
      "A concentration of valuable minerals."
    ]
  },
  {
    "word_no.": 298,
    "word": "MAGMATIC BRECCIA",
    "hints": [
      "A rock composed of angular fragments in an igneous matrix.",
      "Forms from explosive volcanic eruptions.",
      "A type of volcanic rock."
    ]
  },
  {
    "word_no.": 299,
    "word": "MAFIC",
    "hints": [
      "A term for a silicate mineral or rock.",
      "Rich in magnesium and iron.",
      "Examples include basalt and gabbro."
    ]
  },
  {
    "word_no.": 300,
    "word": "MANGANITE",
    "hints": [
      "A manganese oxide mineral.",
      "Has a metallic luster and a brownish-black color.",
      "A minor source of manganese ore."
    ]
  }
]
